Workbook
Name UPDATE: 'Data Sheet'!$E$1

Sheet Profit & Loss
A1: ='Data Sheet'!B1 -> EICHER MOTORS LTD | H1: =UPDATE | M1: SCREENER.IN
A3: Narration | B3: ='Data Sheet'!B16 -> 42460 | C3: ='Data Sheet'!C16 -> 42825 | D3: ='Data Sheet'!D16 -> 43190 | E3: ='Data Sheet'!E16 -> 43555 | F3: ='Data Sheet'!F16 -> 43921 | G3: ='Data Sheet'!G16 -> 44286 | H3: ='Data Sheet'!H16 -> 44651 | I3: ='Data Sheet'!I16 -> 45016 | ... K3: ='Data Sheet'!K16 -> 45747 | L3: Trailing | M3: Best Case | N3: Worst Case
A4: Sales | B4: ='Data Sheet'!B17 -> 6173.46 | C4: ='Data Sheet'!C17 -> 7033.36 | D4: ='Data Sheet'!D17 -> 8964.96 | E4: ='Data Sheet'!E17 -> 9797.06 | F4: ='Data Sheet'!F17 -> 9153.58 | G4: ='Data Sheet'!G17 -> 8720.35 | H4: ='Data Sheet'!H17 -> 10297.83 | I4: ='Data Sheet'!I17 -> 14442.18 | ... K4: ='Data Sheet'!K17 -> 18870.35 | L4: =SUM(Quarters!H4:K4) -> 22568.58 | M4: =$K4+M23*K4 -> 23091.813 | N4: =$K4+N23*L4 -> 21402.143
A5: Expenses | B5: =SUM('Data Sheet'!B18,'Data Sheet'!B20:B24, -1*'Data Sheet'!B19) -> 4483.73 | C5: =SUM('Data Sheet'!C18,'Data Sheet'!C20:C24, -1*'Data Sheet'!C19) -> 4859.05 | D5: =SUM('Data Sheet'!D18,'Data Sheet'!D20:D24, -1*'Data Sheet'!D19) -> 6156.33 | E5: =SUM('Data Sheet'!E18,'Data Sheet'!E20:E24, -1*'Data Sheet'!E19) -> 6892.82 | F5: =SUM('Data Sheet'!F18,'Data Sheet'!F20:F24, -1*'Data Sheet'!F19) -> 6970.69 | G5: =SUM('Data Sheet'!G18,'Data Sheet'!G20:G24, -1*'Data Sheet'!G19) -> 6937.12 | H5: =SUM('Data Sheet'!H18,'Data Sheet'!H20:H24, -1*'Data Sheet'!H19) -> 8120.26 | I5: =SUM('Data Sheet'!I18,'Data Sheet'!I20:I24, -1*'Data Sheet'!I19) -> 10996.46 | ... K5: =SUM('Data Sheet'!K18,'Data Sheet'!K20:K24, -1*'Data Sheet'!K19) -> 14147.78 | L5: =SUM(Quarters!H5:K5) -> 17039.49 | M5: =M4-M6 -> 17302.377 | N5: =N4-N6 -> 16287.227
A6: Operating Profit | B6: =B4-B5 -> 1689.73 | C6: =C4-C5 -> 2174.31 | D6: =D4-D5 -> 2808.63 | E6: =E4-E5 -> 2904.24 | F6: =F4-F5 -> 2182.89 | G6: =G4-G5 -> 1783.23 | H6: =H4-H5 -> 2177.57 | I6: =I4-I5 -> 3445.72 | ... K6: =K4-K5 -> 4722.57 | L6: =SUM(Quarters!H6:K6) -> 5529.09 | M6: =M4*M24 -> 5789.4366 | N6: =N4*N24 -> 5114.9161
A7: Other Income | B7: ='Data Sheet'!B25 -> 325.91 | C7: ='Data Sheet'!C25 -> 416.44 | D7: ='Data Sheet'!D25 -> 535.66 | E7: ='Data Sheet'!E25 -> 700.66 | F7: ='Data Sheet'!F25 -> 572.42 | G7: ='Data Sheet'!G25 -> 482.34 | H7: ='Data Sheet'!H25 -> 495.65 | I7: ='Data Sheet'!I25 -> 908.14 | ... K7: ='Data Sheet'!K25 -> 1994.17 | L7: =SUM(Quarters!H7:K7) -> 2182.23 | M7: 0 | N7: 0
A8: Depreciation | B8: ='Data Sheet'!B26 -> 136.6 | C8: ='Data Sheet'!C26 -> 153.81 | D8: ='Data Sheet'!D26 -> 223.3 | E8: ='Data Sheet'!E26 -> 300.28 | F8: ='Data Sheet'!F26 -> 381.54 | G8: ='Data Sheet'!G26 -> 450.73 | H8: ='Data Sheet'!H26 -> 451.93 | I8: ='Data Sheet'!I26 -> 526.21 | ... K8: ='Data Sheet'!K26 -> 729.33 | L8: =SUM(Quarters!H8:K8) -> 810.09 | M8: =+$L8 -> 810.09 | N8: =+$L8 -> 810.09
A9: Interest | B9: ='Data Sheet'!B27 -> 2.12 | C9: ='Data Sheet'!C27 -> 3.56 | D9: ='Data Sheet'!D27 -> 5.34 | E9: ='Data Sheet'!E27 -> 7.33 | F9: ='Data Sheet'!F27 -> 18.88 | G9: ='Data Sheet'!G27 -> 16.45 | H9: ='Data Sheet'!H27 -> 18.78 | I9: ='Data Sheet'!I27 -> 28.02 | ... K9: ='Data Sheet'!K27 -> 54.34 | L9: =SUM(Quarters!H9:K9) -> 66.87 | M9: =+$L9 -> 66.87 | N9: =+$L9 -> 66.87
A10: Profit before tax | B10: ='Data Sheet'!B28 -> 1876.92 | C10: ='Data Sheet'!C28 -> 2433.38 | D10: ='Data Sheet'!D28 -> 3115.65 | E10: ='Data Sheet'!E28 -> 3297.29 | F10: ='Data Sheet'!F28 -> 2354.89 | G10: ='Data Sheet'!G28 -> 1798.39 | H10: ='Data Sheet'!H28 -> 2202.51 | I10: ='Data Sheet'!I28 -> 3799.63 | ... K10: ='Data Sheet'!K28 -> 5933.07 | L10: =SUM(Quarters!H10:K10) -> 6834.36 | M10: =M6+M7-SUM(M8:M9) -> 4912.4766 | N10: =N6+N7-SUM(N8:N9) -> 4237.9561
A11: Tax | B11: ='Data Sheet'!B29 -> 538.88 | C11: ='Data Sheet'!C29 -> 720.3 | D11: ='Data Sheet'!D29 -> 935.93 | E11: ='Data Sheet'!E29 -> 1077.04 | F11: ='Data Sheet'!F29 -> 527.45 | G11: ='Data Sheet'!G29 -> 451.5 | H11: ='Data Sheet'!H29 -> 525.91 | I11: ='Data Sheet'!I29 -> 885.69 | ... K11: ='Data Sheet'!K29 -> 1198.63 | L11: =SUM(Quarters!H11:K11) -> 1476.93 | M11: =IF($L10>0,$L11/$L10,0) -> 0.21610363 | N11: =IF($L10>0,$L11/$L10,0) -> 0.21610363
A12: Net profit | B12: ='Data Sheet'!B30 -> 1338.04 | C12: ='Data Sheet'!C30 -> 1667.08 | D12: ='Data Sheet'!D30 -> 1959.67 | E12: ='Data Sheet'!E30 -> 2202.73 | F12: ='Data Sheet'!F30 -> 1827.44 | G12: ='Data Sheet'!G30 -> 1346.89 | H12: ='Data Sheet'!H30 -> 1676.6 | I12: ='Data Sheet'!I30 -> 2913.94 | ... K12: ='Data Sheet'!K30 -> 4734.44 | L12: =SUM(Quarters!H12:K12) -> 5357.43 | M12: =M10-M11*M10 -> 3850.8726 | N12: =N10-N11*N10 -> 3322.1184
A13: EPS | B13: =IF('Data Sheet'!B93>0,B12/'Data Sheet'!B93,0) -> 49.265096 | C13: =IF('Data Sheet'!C93>0,C12/'Data Sheet'!C93,0) -> 61.267181 | D13: =IF('Data Sheet'!D93>0,D12/'Data Sheet'!D93,0) -> 71.888114 | E13: =IF('Data Sheet'!E93>0,E12/'Data Sheet'!E93,0) -> 80.745235 | F13: =IF('Data Sheet'!F93>0,F12/'Data Sheet'!F93,0) -> 66.914683 | G13: =IF('Data Sheet'!G93>0,G12/'Data Sheet'!G93,0) -> 49.282473 | H13: =IF('Data Sheet'!H93>0,H12/'Data Sheet'!H93,0) -> 61.324067 | I13: =IF('Data Sheet'!I93>0,I12/'Data Sheet'!I93,0) -> 106.5426 | ... K13: =IF('Data Sheet'!K93>0,K12/'Data Sheet'!K93,0) -> 172.66375 | L13: =IF('Data Sheet'!$B6>0,'Profit & Loss'!L12/'Data Sheet'!$B6,0) -> 195.30565 | M13: =IF('Data Sheet'!$B6>0,'Profit & Loss'!M12/'Data Sheet'!$B6,0) -> 140.38394 | N13: =IF('Data Sheet'!$B6>0,'Profit & Loss'!N12/'Data Sheet'!$B6,0) -> 121.10816
A14: Price to earning | B14: =IF(B15>0,B15/B13,"") -> 38.933447 | C14: =IF(C15>0,C15/C13,"") -> 41.763795 | D14: =IF(D15>0,D15/D13,"") -> 39.467859 | E14: =IF(E15>0,E15/E13,"") -> 25.44757 | F14: =IF(F15>0,F15/F13,"") -> 19.571041 | G14: =IF(G15>0,G15/G13,"") -> 52.837242 | H14: =IF(H15>0,H15/H13,"") -> 40.068282 | I14: =IF(I15>0,I15/I13,"") -> 27.677662 | ... K14: =IF(K15>0,K15/K13,"") -> 30.971759 | L14: =IF(L13>0,L15/L13,0) -> 36.512001 | M14: =M25 -> 36.512001 | N14: =N25 -> 30.666646
A15: Price | B15: ='Data Sheet'!B90 -> 1918.06 | C15: ='Data Sheet'!C90 -> 2558.75 | D15: ='Data Sheet'!D90 -> 2837.27 | E15: ='Data Sheet'!E90 -> 2054.77 | F15: ='Data Sheet'!F90 -> 1309.59 | G15: ='Data Sheet'!G90 -> 2603.95 | H15: ='Data Sheet'!H90 -> 2457.15 | I15: ='Data Sheet'!I90 -> 2948.85 | ... K15: ='Data Sheet'!K90 -> 5347.7 | L15: ='Data Sheet'!B8 -> 7131 | M15: =M13*M14 -> 5125.6987 | N15: =N13*N14 -> 3713.9811
A17: RATIOS:
A18: Dividend Payout | B18: =IF('Data Sheet'!B30>0, 'Data Sheet'!B31/'Data Sheet'!B30, 0) -> 0.20298347 | C18: =IF('Data Sheet'!C30>0, 'Data Sheet'!C31/'Data Sheet'!C30, 0) -> 0.16321952 | D18: =IF('Data Sheet'!D30>0, 'Data Sheet'!D31/'Data Sheet'!D30, 0) -> 0.15301556 | E18: =IF('Data Sheet'!E30>0, 'Data Sheet'!E31/'Data Sheet'!E30, 0) -> 0.1548079 | F18: =IF('Data Sheet'!F30>0, 'Data Sheet'!F31/'Data Sheet'!F30, 0) -> 0.18673664 | G18: =IF('Data Sheet'!G30>0, 'Data Sheet'!G31/'Data Sheet'!G30, 0) -> 0.34495022 | H18: =IF('Data Sheet'!H30>0, 'Data Sheet'!H31/'Data Sheet'!H30, 0) -> 0.34244304 | I18: =IF('Data Sheet'!I30>0, 'Data Sheet'!I31/'Data Sheet'!I30, 0) -> 0.34727894 | ... K18: =IF('Data Sheet'!K30>0, 'Data Sheet'!K31/'Data Sheet'!K30, 0) -> 0.40541226
A19: OPM | B19: =IF(B6>0,B6/B4,0) -> 0.27370875 | C19: =IF(C6>0,C6/C4,0) -> 0.30914243 | D19: =IF(D6>0,D6/D4,0) -> 0.31328974 | E19: =IF(E6>0,E6/E4,0) -> 0.29643995 | F19: =IF(F6>0,F6/F4,0) -> 0.23847391 | G19: =IF(G6>0,G6/G4,0) -> 0.20449065 | H19: =IF(H6>0,H6/H4,0) -> 0.21145911 | I19: =IF(I6>0,I6/I4,0) -> 0.23858725 | ... L19: =IF(L6>0,L6/L4,0) -> 0.2449906
G22: TRENDS: | H22: 10 YEARS | I22: 7 YEARS | J22: 5 YEARS | K22: 3 YEARS | L22: RECENT | M22: BEST | N22: WORST
G23: Sales Growth | H23: =IF(B4=0,"",POWER($K4/B4,1/9)-1) -> 0.13218348 | I23: =IF(D4=0,"",POWER($K4/D4,1/7)-1) -> 0.11218221 | J23: =IF(F4=0,"",POWER($K4/F4,1/5)-1) -> 0.15568052 | K23: =IF(H4=0,"",POWER($K4/H4, 1/3)-1) -> 0.22370879 | L23: =IF(ISERROR(MAX(IF(J4=0,"",(K4-J4)/J4),IF(K4=0,"",(L4-K4)/K4))),"",MAX(IF(J4=0,"",(K4-J4)/J4),IF(K4=0,"",(L4-K4)/K4))) -> 0.195981 | M23: =MAX(K23:L23) -> 0.22370879 | N23: =MIN(H23:L23) -> 0.11218221
G24: OPM | H24: =IF(SUM(B4:$K$4)=0,"",SUMPRODUCT(B19:$K$19,B4:$K$4)/SUM(B4:$K$4)) -> 0.2565555 | I24: =IF(SUM(E4:$K$4)=0,"",SUMPRODUCT(E19:$K$19,E4:$K$4)/SUM(E4:$K$4)) -> 0.2453461 | J24: =IF(SUM(G4:$K$4)=0,"",SUMPRODUCT(G19:$K$19,G4:$K$4)/SUM(G4:$K$4)) -> 0.23899084 | K24: =IF(SUM(I4:$K$4)=0, "", SUMPRODUCT(I19:$K$19,I4:$K$4)/SUM(I4:$K$4)) -> 0.25071382 | L24: =L19 -> 0.2449906 | M24: =MAX(K24:L24) -> 0.25071382 | N24: =MIN(H24:L24) -> 0.23899084
G25: Price to Earning | H25: =IF(ISERROR(AVERAGEIF(B14:$L14,">0")),"",AVERAGEIF(B14:$L14,">0")) -> 34.614166 | I25: =IF(ISERROR(AVERAGEIF(E14:$L14,">0")),"",AVERAGEIF(E14:$L14,">0")) -> 32.57384 | J25: =IF(ISERROR(AVERAGEIF(G14:$L14,">0")),"",AVERAGEIF(G14:$L14,">0")) -> 35.928685 | K25: =IF(ISERROR(AVERAGEIF(I14:$L14,">0")),"",AVERAGEIF(I14:$L14,">0")) -> 30.666646 | L25: =L14 -> 36.512001 | M25: =MAX(K25:L25) -> 36.512001 | N25: =MIN(H25:L25) -> 30.666646

Sheet Quarters
A1: ='Profit & Loss'!A1 -> EICHER MOTORS LTD | E1: =UPDATE | J1: SCREENER.IN
A3: Narration | B3: ='Data Sheet'!B41 -> 45199 | C3: ='Data Sheet'!C41 -> 45291 | D3: ='Data Sheet'!D41 -> 45382 | E3: ='Data Sheet'!E41 -> 45473 | F3: ='Data Sheet'!F41 -> 45565 | G3: ='Data Sheet'!G41 -> 45657 | H3: ='Data Sheet'!H41 -> 45747 | I3: ='Data Sheet'!I41 -> 45838 | ... K3: ='Data Sheet'!K41 -> 46022
A4: Sales | B4: ='Data Sheet'!B42 -> 4114.53 | C4: ='Data Sheet'!C42 -> 4178.84 | D4: ='Data Sheet'!D42 -> 4256.04 | E4: ='Data Sheet'!E42 -> 4393.05 | F4: ='Data Sheet'!F42 -> 4263.07 | G4: ='Data Sheet'!G42 -> 4973.12 | H4: ='Data Sheet'!H42 -> 5241.11 | I4: ='Data Sheet'!I42 -> 5041.84 | ... K4: ='Data Sheet'!K42 -> 6114.04
A5: Expenses | B5: ='Data Sheet'!B43 -> 3027.37 | C5: ='Data Sheet'!C43 -> 3088.57 | D5: ='Data Sheet'!D43 -> 3127.4 | E5: ='Data Sheet'!E43 -> 3227.62 | F5: ='Data Sheet'!F43 -> 3175.35 | G5: ='Data Sheet'!G43 -> 3771.93 | H5: ='Data Sheet'!H43 -> 3983.42 | I5: ='Data Sheet'!I43 -> 3839.06 | ... K5: ='Data Sheet'!K43 -> 4557.32
A6: Operating Profit | B6: ='Data Sheet'!B50 -> 1087.16 | C6: ='Data Sheet'!C50 -> 1090.27 | D6: ='Data Sheet'!D50 -> 1128.64 | E6: ='Data Sheet'!E50 -> 1165.43 | F6: ='Data Sheet'!F50 -> 1087.72 | G6: ='Data Sheet'!G50 -> 1201.19 | H6: ='Data Sheet'!H50 -> 1257.69 | I6: ='Data Sheet'!I50 -> 1202.78 | ... K6: ='Data Sheet'!K50 -> 1556.72
A7: Other Income | B7: ='Data Sheet'!B44 -> 375.4 | C7: ='Data Sheet'!C44 -> 367.58 | D7: ='Data Sheet'!D44 -> 436.96 | E7: ='Data Sheet'!E44 -> 456.51 | F7: ='Data Sheet'!F44 -> 467.53 | G7: ='Data Sheet'!G44 -> 452.29 | H7: ='Data Sheet'!H44 -> 628.38 | I7: ='Data Sheet'!I44 -> 603.17 | ... K7: ='Data Sheet'!K44 -> 464.85
A8: Depreciation | B8: ='Data Sheet'!B45 -> 142.54 | C8: ='Data Sheet'!C45 -> 147.54 | D8: ='Data Sheet'!D45 -> 165.25 | E8: ='Data Sheet'!E45 -> 168.63 | F8: ='Data Sheet'!F45 -> 180.06 | G8: ='Data Sheet'!G45 -> 179.27 | H8: ='Data Sheet'!H45 -> 201.37 | I8: ='Data Sheet'!I45 -> 198.06 | ... K8: ='Data Sheet'!K45 -> 211.1
A9: Interest | B9: ='Data Sheet'!B46 -> 12.68 | C9: ='Data Sheet'!C46 -> 12.43 | D9: ='Data Sheet'!D46 -> 15.34 | E9: ='Data Sheet'!E46 -> 12.27 | F9: ='Data Sheet'!F46 -> 13.14 | G9: ='Data Sheet'!G46 -> 13.39 | H9: ='Data Sheet'!H46 -> 15.54 | I9: ='Data Sheet'!I46 -> 14.9 | ... K9: ='Data Sheet'!K46 -> 17.27
A10: Profit before tax | B10: ='Data Sheet'!B47 -> 1307.34 | C10: ='Data Sheet'!C47 -> 1297.88 | D10: ='Data Sheet'!D47 -> 1385.01 | E10: ='Data Sheet'!E47 -> 1441.04 | F10: ='Data Sheet'!F47 -> 1362.05 | G10: ='Data Sheet'!G47 -> 1460.82 | H10: ='Data Sheet'!H47 -> 1669.16 | I10: ='Data Sheet'!I47 -> 1592.99 | ... K10: ='Data Sheet'!K47 -> 1793.2
A11: Tax | B11: ='Data Sheet'!B48 -> 291.09 | C11: ='Data Sheet'!C48 -> 301.91 | D11: ='Data Sheet'!D48 -> 314.56 | E11: ='Data Sheet'!E48 -> 339.58 | F11: ='Data Sheet'!F48 -> 261.72 | G11: ='Data Sheet'!G48 -> 290.32 | H11: ='Data Sheet'!H48 -> 307.01 | I11: ='Data Sheet'!I48 -> 387.77 | ... K11: ='Data Sheet'!K48 -> 372.59
A12: Net profit | B12: ='Data Sheet'!B49 -> 1016.25 | C12: ='Data Sheet'!C49 -> 995.97 | D12: ='Data Sheet'!D49 -> 1070.45 | E12: ='Data Sheet'!E49 -> 1101.46 | F12: ='Data Sheet'!F49 -> 1100.33 | G12: ='Data Sheet'!G49 -> 1170.5 | H12: ='Data Sheet'!H49 -> 1362.15 | I12: ='Data Sheet'!I49 -> 1205.22 | ... K12: ='Data Sheet'!K49 -> 1420.61
A14: OPM | B14: =IF(B4>0,B6/B4,"") -> 0.26422459 | C14: =IF(C4>0,C6/C4,"") -> 0.26090255 | D14: =IF(D4>0,D6/D4,"") -> 0.26518548 | E14: =IF(E4>0,E6/E4,"") -> 0.26528949 | F14: =IF(F4>0,F6/F4,"") -> 0.25514946 | G14: =IF(G4>0,G6/G4,"") -> 0.2415365 | H14: =IF(H4>0,H6/H4,"") -> 0.23996634 | I14: =IF(I4>0,I6/I4,"") -> 0.23855973 | ... K14: =IF(K4>0,K6/K4,"") -> 0.25461397

Sheet Balance Sheet
A1: ='Profit & Loss'!A1 -> EICHER MOTORS LTD | E1: =UPDATE | J1: SCREENER.IN
A3: Narration | B3: ='Data Sheet'!B56 -> 42460 | C3: ='Data Sheet'!C56 -> 42825 | D3: ='Data Sheet'!D56 -> 43190 | E3: ='Data Sheet'!E56 -> 43555 | F3: ='Data Sheet'!F56 -> 43921 | G3: ='Data Sheet'!G56 -> 44286 | H3: ='Data Sheet'!H56 -> 44651 | I3: ='Data Sheet'!I56 -> 45016 | ... K3: ='Data Sheet'!K56 -> 45747
A4: Equity Share Capital | B4: ='Data Sheet'!B57 -> 27.16 | C4: ='Data Sheet'!C57 -> 27.21 | D4: ='Data Sheet'!D57 -> 27.26 | E4: ='Data Sheet'!E57 -> 27.28 | F4: ='Data Sheet'!F57 -> 27.3 | G4: ='Data Sheet'!G57 -> 27.33 | H4: ='Data Sheet'!H57 -> 27.34 | I4: ='Data Sheet'!I57 -> 27.35 | ... K4: ='Data Sheet'!K57 -> 27.42
A5: Reserves | B5: ='Data Sheet'!B58 -> 3625.93 | C5: ='Data Sheet'!C58 -> 5317.86 | D5: ='Data Sheet'!D58 -> 7002.81 | E5: ='Data Sheet'!E58 -> 8891.44 | F5: ='Data Sheet'!F58 -> 9953.63 | G5: ='Data Sheet'!G58 -> 11410.75 | H5: ='Data Sheet'!H58 -> 12580.66 | I5: ='Data Sheet'!I58 -> 14962.93 | ... K5: ='Data Sheet'!K58 -> 21269.07
A6: Borrowings | B6: ='Data Sheet'!B59 -> 22.57 | C6: ='Data Sheet'!C59 -> 111.85 | D6: ='Data Sheet'!D59 -> 150.84 | E6: ='Data Sheet'!E59 -> 186.76 | F6: ='Data Sheet'!F59 -> 249 | G6: ='Data Sheet'!G59 -> 219.25 | H6: ='Data Sheet'!H59 -> 107.71 | I6: ='Data Sheet'!I59 -> 288.41 | ... K6: ='Data Sheet'!K59 -> 458.13
A7: Other Liabilities | B7: ='Data Sheet'!B60 -> 1263.35 | C7: ='Data Sheet'!C60 -> 1552.16 | D7: ='Data Sheet'!D60 -> 2341.32 | E7: ='Data Sheet'!E60 -> 2281.35 | F7: ='Data Sheet'!F60 -> 2219.79 | G7: ='Data Sheet'!G60 -> 2901.28 | H7: ='Data Sheet'!H60 -> 3424.12 | I7: ='Data Sheet'!I60 -> 3918.95 | ... K7: ='Data Sheet'!K60 -> 5419.79
A8: Total | B8: ='Data Sheet'!B61 -> 4939.01 | C8: ='Data Sheet'!C61 -> 7009.08 | D8: ='Data Sheet'!D61 -> 9522.23 | E8: ='Data Sheet'!E61 -> 11386.83 | F8: ='Data Sheet'!F61 -> 12449.72 | G8: ='Data Sheet'!G61 -> 14558.61 | H8: ='Data Sheet'!H61 -> 16139.83 | I8: ='Data Sheet'!I61 -> 19197.64 | ... K8: ='Data Sheet'!K61 -> 27174.41
A10: Net Block | B10: ='Data Sheet'!B62 -> 789.59 | C10: ='Data Sheet'!C62 -> 872.78 | D10: ='Data Sheet'!D62 -> 1501.69 | E10: ='Data Sheet'!E62 -> 1874.58 | F10: ='Data Sheet'!F62 -> 2377.52 | G10: ='Data Sheet'!G62 -> 2433.3 | H10: ='Data Sheet'!H62 -> 2424.28 | I10: ='Data Sheet'!I62 -> 2689.99 | ... K10: ='Data Sheet'!K62 -> 3473.47
A11: Capital Work in Progress | B11: ='Data Sheet'!B63 -> 94.48 | C11: ='Data Sheet'!C63 -> 373.77 | D11: ='Data Sheet'!D63 -> 333.21 | E11: ='Data Sheet'!E63 -> 449.74 | F11: ='Data Sheet'!F63 -> 312.17 | G11: ='Data Sheet'!G63 -> 314.29 | H11: ='Data Sheet'!H63 -> 504.78 | I11: ='Data Sheet'!I63 -> 472.07 | ... K11: ='Data Sheet'!K63 -> 491.47
A12: Investments | B12: ='Data Sheet'!B64 -> 3388.24 | C12: ='Data Sheet'!C64 -> 4987.13 | D12: ='Data Sheet'!D64 -> 5580.84 | E12: ='Data Sheet'!E64 -> 4922.52 | F12: ='Data Sheet'!F64 -> 5748.77 | G12: ='Data Sheet'!G64 -> 3902.14 | H12: ='Data Sheet'!H64 -> 7720.58 | I12: ='Data Sheet'!I64 -> 12320.66 | ... K12: ='Data Sheet'!K64 -> 14790.9
A13: Other Assets | B13: ='Data Sheet'!B65 -> 666.7 | C13: ='Data Sheet'!C65 -> 775.4 | D13: ='Data Sheet'!D65 -> 2106.49 | E13: ='Data Sheet'!E65 -> 4139.99 | F13: ='Data Sheet'!F65 -> 4011.26 | G13: ='Data Sheet'!G65 -> 7908.88 | H13: ='Data Sheet'!H65 -> 5490.19 | I13: ='Data Sheet'!I65 -> 3714.92 | ... K13: ='Data Sheet'!K65 -> 8418.57
A14: Total | B14: ='Data Sheet'!B66 -> 4939.01 | C14: ='Data Sheet'!C66 -> 7009.08 | D14: ='Data Sheet'!D66 -> 9522.23 | E14: ='Data Sheet'!E66 -> 11386.83 | F14: ='Data Sheet'!F66 -> 12449.72 | G14: ='Data Sheet'!G66 -> 14558.61 | H14: ='Data Sheet'!H66 -> 16139.83 | I14: ='Data Sheet'!I66 -> 19197.64 | ... K14: ='Data Sheet'!K66 -> 27174.41
A16: Working Capital | B16: =B13-B7 -> -596.65 | C16: =C13-C7 -> -776.76 | D16: =D13-D7 -> -234.83 | E16: =E13-E7 -> 1858.64 | F16: =F13-F7 -> 1791.47 | G16: =G13-G7 -> 5007.6 | H16: =H13-H7 -> 2066.07 | I16: =I13-I7 -> -204.03 | ... K16: =K13-K7 -> 2998.78
A17: Debtors | B17: ='Data Sheet'!B67 -> 32.64 | C17: ='Data Sheet'!C67 -> 50.04 | D17: ='Data Sheet'!D67 -> 68 | E17: ='Data Sheet'!E67 -> 84.29 | F17: ='Data Sheet'!F67 -> 86.76 | G17: ='Data Sheet'!G67 -> 158.16 | H17: ='Data Sheet'!H67 -> 302.04 | I17: ='Data Sheet'!I67 -> 368.92 | ... K17: ='Data Sheet'!K67 -> 549.64
A18: Inventory | B18: ='Data Sheet'!B68 -> 308.39 | C18: ='Data Sheet'!C68 -> 335.9 | D18: ='Data Sheet'!D68 -> 394.64 | E18: ='Data Sheet'!E68 -> 633.38 | F18: ='Data Sheet'!F68 -> 572.35 | G18: ='Data Sheet'!G68 -> 874.6 | H18: ='Data Sheet'!H68 -> 1132.4 | I18: ='Data Sheet'!I68 -> 1278.44 | ... K18: ='Data Sheet'!K68 -> 1563.75
A20: Debtor Days | B20: =IF('Profit & Loss'!B4>0,'Balance Sheet'!B17/('Profit & Loss'!B4/365),0) -> 1.9298092 | C20: =IF('Profit & Loss'!C4>0,'Balance Sheet'!C17/('Profit & Loss'!C4/365),0) -> 2.5968527 | D20: =IF('Profit & Loss'!D4>0,'Balance Sheet'!D17/('Profit & Loss'!D4/365),0) -> 2.7685567 | E20: =IF('Profit & Loss'!E4>0,'Balance Sheet'!E17/('Profit & Loss'!E4/365),0) -> 3.1403145 | F20: =IF('Profit & Loss'!F4>0,'Balance Sheet'!F17/('Profit & Loss'!F4/365),0) -> 3.4595645 | G20: =IF('Profit & Loss'!G4>0,'Balance Sheet'!G17/('Profit & Loss'!G4/365),0) -> 6.6199636 | H20: =IF('Profit & Loss'!H4>0,'Balance Sheet'!H17/('Profit & Loss'!H4/365),0) -> 10.705615 | I20: =IF('Profit & Loss'!I4>0,'Balance Sheet'!I17/('Profit & Loss'!I4/365),0) -> 9.3237863 | ... K20: =IF('Profit & Loss'!K4>0,'Balance Sheet'!K17/('Profit & Loss'!K4/365),0) -> 10.631419
A21: Inventory Turnover | B21: =IF('Balance Sheet'!B18>0,'Profit & Loss'!B4/'Balance Sheet'!B18,0) -> 20.018353 | C21: =IF('Balance Sheet'!C18>0,'Profit & Loss'!C4/'Balance Sheet'!C18,0) -> 20.938851 | D21: =IF('Balance Sheet'!D18>0,'Profit & Loss'!D4/'Balance Sheet'!D18,0) -> 22.716805 | E21: =IF('Balance Sheet'!E18>0,'Profit & Loss'!E4/'Balance Sheet'!E18,0) -> 15.467902 | F21: =IF('Balance Sheet'!F18>0,'Profit & Loss'!F4/'Balance Sheet'!F18,0) -> 15.992976 | G21: =IF('Balance Sheet'!G18>0,'Profit & Loss'!G4/'Balance Sheet'!G18,0) -> 9.9706723 | H21: =IF('Balance Sheet'!H18>0,'Profit & Loss'!H4/'Balance Sheet'!H18,0) -> 9.0938096 | I21: =IF('Balance Sheet'!I18>0,'Profit & Loss'!I4/'Balance Sheet'!I18,0) -> 11.296721 | ... K21: =IF('Balance Sheet'!K18>0,'Profit & Loss'!K4/'Balance Sheet'!K18,0) -> 12.06737
A23: Return on Equity | B23: =IF(SUM('Balance Sheet'!B4:B5)>0,'Profit & Loss'!B12/SUM('Balance Sheet'!B4:B5),"") -> 0.36627622 | C23: =IF(SUM('Balance Sheet'!C4:C5)>0,'Profit & Loss'!C12/SUM('Balance Sheet'!C4:C5),"") -> 0.31189114 | D23: =IF(SUM('Balance Sheet'!D4:D5)>0,'Profit & Loss'!D12/SUM('Balance Sheet'!D4:D5),"") -> 0.2787554 | E23: =IF(SUM('Balance Sheet'!E4:E5)>0,'Profit & Loss'!E12/SUM('Balance Sheet'!E4:E5),"") -> 0.24697827 | F23: =IF(SUM('Balance Sheet'!F4:F5)>0,'Profit & Loss'!F12/SUM('Balance Sheet'!F4:F5),"") -> 0.18309316 | G23: =IF(SUM('Balance Sheet'!G4:G5)>0,'Profit & Loss'!G12/SUM('Balance Sheet'!G4:G5),"") -> 0.1177549 | H23: =IF(SUM('Balance Sheet'!H4:H5)>0,'Profit & Loss'!H12/SUM('Balance Sheet'!H4:H5),"") -> 0.13297906 | I23: =IF(SUM('Balance Sheet'!I4:I5)>0,'Profit & Loss'!I12/SUM('Balance Sheet'!I4:I5),"") -> 0.19438863 | ... K23: =IF(SUM('Balance Sheet'!K4:K5)>0,'Profit & Loss'!K12/SUM('Balance Sheet'!K4:K5),"") -> 0.22231081
A24: Return on Capital Emp | C24: =IF((B4+B5+B6+C4+C5+C6)>0,('Profit & Loss'!C10+'Profit & Loss'!C9)*2/(B4+B5+B6+C4+C5+C6),"") -> 0.53368052 | D24: =IF((C4+C5+C6+D4+D5+D6)>0,('Profit & Loss'!D10+'Profit & Loss'!D9)*2/(C4+C5+C6+D4+D5+D6),"") -> 0.49391233 | E24: =IF((D4+D5+D6+E4+E5+E6)>0,('Profit & Loss'!E10+'Profit & Loss'!E9)*2/(D4+D5+D6+E4+E5+E6),"") -> 0.40581369 | F24: =IF((E4+E5+E6+F4+F5+F6)>0,('Profit & Loss'!F10+'Profit & Loss'!F9)*2/(E4+E5+E6+F4+F5+F6),"") -> 0.24553604 | G24: =IF((F4+F5+F6+G4+G5+G6)>0,('Profit & Loss'!G10+'Profit & Loss'!G9)*2/(F4+F5+F6+G4+G5+G6),"") -> 0.16583529 | H24: =IF((G4+G5+G6+H4+H5+H6)>0,('Profit & Loss'!H10+'Profit & Loss'!H9)*2/(G4+G5+G6+H4+H5+H6),"") -> 0.18227435 | I24: =IF((H4+H5+H6+I4+I5+I6)>0,('Profit & Loss'!I10+'Profit & Loss'!I9)*2/(H4+H5+H6+I4+I5+I6),"") -> 0.27345826 | J24: =IF((I4+I5+I6+J4+J5+J6)>0,('Profit & Loss'!J10+'Profit & Loss'!J9)*2/(I4+I5+I6+J4+J5+J6),"") -> 0.31134145 | K24: =IF((J4+J5+J6+K4+K5+K6)>0,('Profit & Loss'!K10+'Profit & Loss'!K9)*2/(J4+J5+J6+K4+K5+K6),"") -> 0.297736

Sheet Cash Flow
A1: ='Balance Sheet'!A1 -> EICHER MOTORS LTD | E1: =UPDATE | J1: SCREENER.IN
A3: Narration | B3: ='Data Sheet'!B81 -> 42460 | C3: ='Data Sheet'!C81 -> 42825 | D3: ='Data Sheet'!D81 -> 43190 | E3: ='Data Sheet'!E81 -> 43555 | F3: ='Data Sheet'!F81 -> 43921 | G3: ='Data Sheet'!G81 -> 44286 | H3: ='Data Sheet'!H81 -> 44651 | I3: ='Data Sheet'!I81 -> 45016 | ... K3: ='Data Sheet'!K81 -> 45747
A4: Cash from Operating Activity | B4: ='Data Sheet'!B82 -> 1463.08 | C4: ='Data Sheet'!C82 -> 1707.97 | D4: ='Data Sheet'!D82 -> 2482.25 | E4: ='Data Sheet'!E82 -> 1575.47 | F4: ='Data Sheet'!F82 -> 1694.12 | G4: ='Data Sheet'!G82 -> 1690.97 | H4: ='Data Sheet'!H82 -> 1527.04 | I4: ='Data Sheet'!I82 -> 2822.66 | ... K4: ='Data Sheet'!K82 -> 3979.92
A5: Cash from Investing Activity | B5: ='Data Sheet'!B83 -> -1001.4 | C5: ='Data Sheet'!C83 -> -1743.58 | D5: ='Data Sheet'!D83 -> -2145.02 | E5: ='Data Sheet'!E83 -> -659.88 | F5: ='Data Sheet'!F83 -> -1508.41 | G5: ='Data Sheet'!G83 -> -1625.3 | H5: ='Data Sheet'!H83 -> -983.25 | I5: ='Data Sheet'!I83 -> -2396.8 | ... K5: ='Data Sheet'!K83 -> -2460.68
A6: Cash from Financing Activity | B6: ='Data Sheet'!B84 -> -465.52 | C6: ='Data Sheet'!C84 -> 25.29 | D6: ='Data Sheet'!D84 -> -262.01 | E6: ='Data Sheet'!E84 -> -292.3 | F6: ='Data Sheet'!F84 -> -858.25 | G6: ='Data Sheet'!G84 -> -14.76 | H6: ='Data Sheet'!H84 -> -593.36 | I6: ='Data Sheet'!I84 -> -417.44 | ... K6: ='Data Sheet'!K84 -> -1398.67
A7: Net Cash Flow | B7: ='Data Sheet'!B85 -> -3.84 | C7: ='Data Sheet'!C85 -> -10.32 | D7: ='Data Sheet'!D85 -> 75.22 | E7: ='Data Sheet'!E85 -> 623.29 | F7: ='Data Sheet'!F85 -> -672.54 | G7: ='Data Sheet'!G85 -> 50.91 | H7: ='Data Sheet'!H85 -> -49.57 | I7: ='Data Sheet'!I85 -> 8.42 | ... K7: ='Data Sheet'!K85 -> 120.57

Sheet Customization
A1: How to use it?
A3: You can customize this workbook as you want.
B4: You can add custom formating, add conditional formating, add your own formulas… do ANYTHING.
B5: Please don't edit the "Data Sheet" only.
A7: After customization, you can upload this back on Screener.
B8: Upload on: | C8: https://www.screener.in/excel/
A10: Download your customized workbooks now onwards.
B11: Now whenever you will "Export to excel" from Screener, it will export your customized file.
A14: TESTING:
B15: This is a testing feature currently.
B16: You can report any formula errors on the worksheet at: support@screener.in

Sheet Data Sheet
A1: COMPANY NAME | B1: EICHER MOTORS LTD | E1: =IF(B2<>B3, "A NEW VERSION OF THE WORKSHEET IS AVAILABLE", "")
A2: LATEST VERSION | B2: 2.1 | E2: PLEASE DO NOT MAKE ANY CHANGES TO THIS SHEET
A3: CURRENT VERSION | B3: 2.1
A5: META
A6: Number of shares | B6: =IF(B9>0, B9/B8, 0) -> 27.431004
A7: Face Value | B7: 1
A8: Current Price | B8: 7131
A9: Market Capitalization | B9: 195610.49
A15: PROFIT & LOSS
A16: Report Date | B16: 42460 | C16: 42825 | D16: 43190 | E16: 43555 | F16: 43921 | G16: 44286 | H16: 44651 | I16: 45016 | J16: 45382 | K16: 45747
A17: Sales | B17: 6173.46 | C17: 7033.36 | D17: 8964.96 | E17: 9797.06 | F17: 9153.58 | G17: 8720.35 | H17: 10297.83 | I17: 14442.18 | J17: 16535.78 | K17: 18870.35
A18: Raw Material Cost | B18: 3497.73 | C18: 3725.72 | D18: 4679.07 | E18: 5269.64 | F18: 4914.58 | G18: 5319.85 | H18: 6107.28 | I18: 8281.04 | J18: 9187.35 | K18: 10470.09
A19: Change in Inventory | B19: 62.05 | C19: 19.61 | D19: 33.87 | E19: 210.16 | F19: -84.09 | G19: 205.9 | H19: 148.59 | I19: 63.25 | J19: 197.03 | K19: 163.51
A20: Power and Fuel | B20: 46.18 | C20: 46.02 | D20: 52.41 | E20: 66.96 | F20: 62.86 | G20: 52.98 | H20: 55.78 | I20: 72.97 | J20: 80.61 | K20: 89.53
A21: Other Mfr. Exp | B21: 173.76 | C21: 173.09 | D21: 210.76 | E21: 263.49 | F21: 256.58 | G21: 250.85 | H21: 332.41 | I21: 397.21 | J21: 394.36 | K21: 453.77
A22: Employee Cost | B22: 350.21 | C22: 426.28 | D22: 573.68 | E22: 702.44 | F22: 795.78 | G22: 843.23 | H22: 821.02 | I22: 1001.93 | J22: 1235.69 | K22: 1391.23
A23: Selling and admin | B23: 397.4 | C23: 412.25 | D23: 565.66 | E23: 654.82 | F23: 667.16 | G23: 522.52 | H23: 815.51 | I23: 1164.58 | J23: 1293.02 | K23: 1669.63
A24: Other Expenses | B24: 80.5 | C24: 95.3 | D24: 108.62 | E24: 145.63 | F24: 189.64 | G24: 153.59 | H24: 136.85 | I24: 141.98 | J24: 212.41 | K24: 237.04
A25: Other Income | B25: 325.91 | C25: 416.44 | D25: 535.66 | E25: 700.66 | F25: 572.42 | G25: 482.34 | H25: 495.65 | I25: 908.14 | J25: 1521.13 | K25: 1994.17
A26: Depreciation | B26: 136.6 | C26: 153.81 | D26: 223.3 | E26: 300.28 | F26: 381.54 | G26: 450.73 | H26: 451.93 | I26: 526.21 | J26: 597.6 | K26: 729.33
A27: Interest | B27: 2.12 | C27: 3.56 | D27: 5.34 | E27: 7.33 | F27: 18.88 | G27: 16.45 | H27: 18.78 | I27: 28.02 | J27: 50.88 | K27: 54.34
... A31: Dividend Amount | B31: 271.6 | C31: 272.1 | D31: 299.86 | E31: 341 | F31: 341.25 | G31: 464.61 | H31: 574.14 | I31: 1011.95 | J31: 1396.38 | K31: 1919.4
A40: Quarters
A41: Report Date | B41: 45199 | C41: 45291 | D41: 45382 | E41: 45473 | F41: 45565 | G41: 45657 | H41: 45747 | I41: 45838 | J41: 45930 | K41: 46022
A42: Sales | B42: 4114.53 | C42: 4178.84 | D42: 4256.04 | E42: 4393.05 | F42: 4263.07 | G42: 4973.12 | H42: 5241.11 | I42: 5041.84 | J42: 6171.59 | K42: 6114.04
A43: Expenses | B43: 3027.37 | C43: 3088.57 | D43: 3127.4 | E43: 3227.62 | F43: 3175.35 | G43: 3771.93 | H43: 3983.42 | I43: 3839.06 | J43: 4659.69 | K43: 4557.32
A44: Other Income | B44: 375.4 | C44: 367.58 | D44: 436.96 | E44: 456.51 | F44: 467.53 | G44: 452.29 | H44: 628.38 | I44: 603.17 | J44: 485.83 | K44: 464.85
A45: Depreciation | B45: 142.54 | C45: 147.54 | D45: 165.25 | E45: 168.63 | F45: 180.06 | G45: 179.27 | H45: 201.37 | I45: 198.06 | J45: 199.56 | K45: 211.1
A46: Interest | B46: 12.68 | C46: 12.43 | D46: 15.34 | E46: 12.27 | F46: 13.14 | G46: 13.39 | H46: 15.54 | I46: 14.9 | J46: 19.16 | K46: 17.27
A47: Profit before tax | B47: 1307.34 | C47: 1297.88 | D47: 1385.01 | E47: 1441.04 | F47: 1362.05 | G47: 1460.82 | H47: 1669.16 | I47: 1592.99 | J47: 1779.01 | K47: 1793.2
A48: Tax | B48: 291.09 | C48: 301.91 | D48: 314.56 | E48: 339.58 | F48: 261.72 | G48: 290.32 | H48: 307.01 | I48: 387.77 | J48: 409.56 | K48: 372.59
A49: Net profit | B49: 1016.25 | C49: 995.97 | D49: 1070.45 | E49: 1101.46 | F49: 1100.33 | G49: 1170.5 | H49: 1362.15 | I49: 1205.22 | J49: 1369.45 | K49: 1420.61
A50: Operating Profit | B50: 1087.16 | C50: 1090.27 | D50: 1128.64 | E50: 1165.43 | F50: 1087.72 | G50: 1201.19 | H50: 1257.69 | I50: 1202.78 | J50: 1511.9 | K50: 1556.72
A55: BALANCE SHEET
A56: Report Date | B56: 42460 | C56: 42825 | D56: 43190 | E56: 43555 | F56: 43921 | G56: 44286 | H56: 44651 | I56: 45016 | J56: 45382 | K56: 45747
A57: Equity Share Capital | B57: 27.16 | C57: 27.21 | D57: 27.26 | E57: 27.28 | F57: 27.3 | G57: 27.33 | H57: 27.34 | I57: 27.35 | J57: 27.38 | K57: 27.42
A58: Reserves | B58: 3625.93 | C58: 5317.86 | D58: 7002.81 | E58: 8891.44 | F58: 9953.63 | G58: 11410.75 | H58: 12580.66 | I58: 14962.93 | J58: 18018.15 | K58: 21269.07
A59: Borrowings | B59: 22.57 | C59: 111.85 | D59: 150.84 | E59: 186.76 | F59: 249 | G59: 219.25 | H59: 107.71 | I59: 288.41 | J59: 419.44 | K59: 458.13
A60: Other Liabilities | B60: 1263.35 | C60: 1552.16 | D60: 2341.32 | E60: 2281.35 | F60: 2219.79 | G60: 2901.28 | H60: 3424.12 | I60: 3918.95 | J60: 4650.16 | K60: 5419.79
A61: Total | B61: 4939.01 | C61: 7009.08 | D61: 9522.23 | E61: 11386.83 | F61: 12449.72 | G61: 14558.61 | H61: 16139.83 | I61: 19197.64 | J61: 23115.13 | K61: 27174.41
A62: Net Block | B62: 789.59 | C62: 872.78 | D62: 1501.69 | E62: 1874.58 | F62: 2377.52 | G62: 2433.3 | H62: 2424.28 | I62: 2689.99 | J62: 2914.38 | K62: 3473.47
A63: Capital Work in Progress | B63: 94.48 | C63: 373.77 | D63: 333.21 | E63: 449.74 | F63: 312.17 | G63: 314.29 | H63: 504.78 | I63: 472.07 | J63: 555.1 | K63: 491.47
A64: Investments | B64: 3388.24 | C64: 4987.13 | D64: 5580.84 | E64: 4922.52 | F64: 5748.77 | G64: 3902.14 | H64: 7720.58 | I64: 12320.66 | J64: 13526.96 | K64: 14790.9
A65: Other Assets | B65: 666.7 | C65: 775.4 | D65: 2106.49 | E65: 4139.99 | F65: 4011.26 | G65: 7908.88 | H65: 5490.19 | I65: 3714.92 | J65: 6118.69 | K65: 8418.57
A66: Total | B66: 4939.01 | C66: 7009.08 | D66: 9522.23 | E66: 11386.83 | F66: 12449.72 | G66: 14558.61 | H66: 16139.83 | I66: 19197.64 | J66: 23115.13 | K66: 27174.41
A67: Receivables | B67: 32.64 | C67: 50.04 | D67: 68 | E67: 84.29 | F67: 86.76 | G67: 158.16 | H67: 302.04 | I67: 368.92 | J67: 373.78 | K67: 549.64
... A70: No. of Equity Shares | B70: 27161183 | C70: 27210249 | D70: 27255549 | E70: 27282570 | F70: 27304570 | G70: 273335922 | H70: 273423102 | I70: 273481570 | J70: 273805630 | K70: 274164080
A71: New Bonus Shares
A72: Face value | B72: 10 | C72: 10 | D72: 10 | E72: 10 | F72: 10 | G72: 1 | H72: 1 | I72: 1 | J72: 1 | K72: 1
A80: CASH FLOW:
A81: Report Date | B81: 42460 | C81: 42825 | D81: 43190 | E81: 43555 | F81: 43921 | G81: 44286 | H81: 44651 | I81: 45016 | J81: 45382 | K81: 45747
A82: Cash from Operating Activity | B82: 1463.08 | C82: 1707.97 | D82: 2482.25 | E82: 1575.47 | F82: 1694.12 | G82: 1690.97 | H82: 1527.04 | I82: 2822.66 | J82: 3723.71 | K82: 3979.92
A83: Cash from Investing Activity | B83: -1001.4 | C83: -1743.58 | D83: -2145.02 | E83: -659.88 | F83: -1508.41 | G83: -1625.3 | H83: -983.25 | I83: -2396.8 | J83: -2833.93 | K83: -2460.68
A84: Cash from Financing Activity | B84: -465.52 | C84: 25.29 | D84: -262.01 | E84: -292.3 | F84: -858.25 | G84: -14.76 | H84: -593.36 | I84: -417.44 | J84: -844.36 | K84: -1398.67
A85: Net Cash Flow | B85: -3.84 | C85: -10.32 | D85: 75.22 | E85: 623.29 | F85: -672.54 | G85: 50.91 | H85: -49.57 | I85: 8.42 | J85: 45.42 | K85: 120.57
A90: PRICE: | B90: 1918.06 | C90: 2558.75 | D90: 2837.27 | E90: 2054.77 | F90: 1309.59 | G90: 2603.95 | H90: 2457.15 | I90: 2948.85 | J90: 4019.3 | K90: 5347.7
A92: DERIVED:
A93: Adjusted Equity Shares in Cr | B93: 27.16 | C93: 27.21 | D93: 27.26 | E93: 27.28 | F93: 27.31 | G93: 27.33 | H93: 27.34 | I93: 27.35 | J93: 27.38 | K93: 27.42

Sheet Data
B1: Automobile Industry peers in India ( From screener .in)
B2: S.No. | C2: Name | D2: CMP Rs. | E2: Mar Cap Rs.Cr. | F2: Debt Rs.Cr. | G2: Debt / Eq | H2: Eq Cap Rs.Cr.
B3: 1 | C3: Bajaj Auto | D3: 9861 | E3: 275722.37 | F3: 19693.24 | G3: 0.58 | H3: 279.5
B4: 2 | C4: Eicher Motors | D4: 7128.05 | E4: 195532.53 | F4: 445.78 | G4: 0.02 | H4: 27.43
B5: 3 | C5: TVS Motor Co. | D5: 3780.1 | E5: 179587.67 | F5: 31589.29 | G5: 3.89 | H5: 47.51
B6: 4 | C6: Hero Motocorp | D6: 5284.9 | E6: 105745.47 | F6: 718.07 | G6: 0.03 | H6: 40.02

Sheet Cashflow raw data
B2: 41609 | C2: 41974 | D2: 42430 | E2: 42795 | F2: 43160 | G2: 43525 | H2: 43891 | I2: 44256 | J2: 44621 | K2: 44986 | L2: 45352 | M2: 45717
B3: Cash from Operating Activity - | C3: 716 | D3: 1047 | E3: 1463 | F3: 1708 | G3: 2482 | H3: 1575 | I3: 1694 | J3: 1691 | K3: 1527 | L3: 2823 | M3: 3724 | N3: 3980
B4: Profit from operations | C4: 718 | D4: 1126 | E4: 1719 | F4: 2196 | G4: 2851 | H4: 2941 | I4: 2236 | J4: 1912 | K4: 2172 | L4: 3527 | M4: 4404 | N4: 4849
B5: Receivables | C5: -67 | D5: -50 | E5: -22 | F5: -17 | G5: -18 | H5: -18 | I5: 0 | J5: -73 | K5: -147 | L5: -59 | M5: -5 | N5: -176
B6: Inventory | C6: -38 | D6: -119 | E6: -104 | F6: -28 | G6: -59 | H6: -239 | I6: 61 | J6: -302 | K6: -258 | L6: -146 | M6: -131 | N6: -154
B7: Payables | C7: 237 | D7: 321 | E7: 241 | F7: 110 | G7: 407 | H7: 62 | I7: -235 | J7: 495 | K7: 283 | L7: 22 | M7: 304 | N7: 440
B8: Loans Advances | C8: -20 | D8: -103 | E8: -12 | F8: 6 | G8: 0 | H8: -1 | I8: 1 | J8: 0 | K8: 0 | L8: 0 | M8: 0 | N8: 0
B9: Other WC items | C9: 37 | D9: 152 | E9: 160 | F9: 92 | G9: 109 | H9: -262 | I9: 259 | J9: 115 | K9: -10 | L9: 249 | M9: 220 | N9: 101
B10: Working capital changes | C10: 149 | D10: 202 | E10: 263 | F10: 163 | G10: 438 | H10: -457 | I10: 86 | J10: 235 | K10: -131 | L10: 66 | M10: 388 | N10: 211
B11: Direct taxes | C11: -150 | D11: -281 | E11: -519 | F11: -652 | G11: -807 | H11: -908 | I11: -628 | J11: -457 | K11: -514 | L11: -770 | M11: -1068 | N11: -1080
B12: Cash from Investing Activity - | C12: -790 | D12: -1214 | E12: -1001 | F12: -1744 | G12: -2145 | H12: -660 | I12: -1508 | J12: -1625 | K12: -983 | L12: -2397 | M12: -2834 | N12: -2461
B13: Fixed assets purchased | C13: -712 | D13: -972 | E13: -510 | F13: -548 | G13: -748 | H13: -792 | I13: -546 | J13: -532 | K13: -641 | L13: -682 | M13: -819 | N13: -1039
B14: Fixed assets sold | C14: 7 | D14: 4 | E14: 1 | F14: 1 | G14: 3 | H14: 2 | I14: 1 | J14: 17 | K14: 2 | L14: 9 | M14: 4 | N14: 11
... B29: Net Cash Flow | C29: -121 | D29: -329 | E29: -4 | F29: -10 | G29: 75 | H29: 623 | I29: -673 | J29: 51 | K29: -50 | L29: 8 | M29: 45 | N29: 121

Sheet Rm calculation 
B2: Visit Prime investors.in
B4: Year | C4: Annual | E4: 25-Year Average Return | F4: =AVERAGE(C5:C30) -> 0.15149231
B5: 2000 | C5: -0.1465 | E5: Add Dividend Yield | F5: 0.0128
B6: 2001 | C6: -0.1618 | E6: Rm | F6: =SUM(F4:F5) -> 0.16429231
B7: 2002 | C7: 0.0325
B8: 2003 | C8: 0.719
B9: 2004 | C9: 0.1068
B10: 2005 | C10: 0.3634
B11: 2006 | C11: 0.3983
B12: 2007 | C12: 0.5477
B13: 2008 | C13: -0.5179
B14: 2009 | C14: 0.7576
B15: 2010 | C15: 0.1795
B16: 2011 | C16: -0.2462
B17: 2012 | C17: 0.277
B18: 2013 | C18: 0.0676
... B30: 2025 | C30: 0.1051

Sheet Raw Data
B1: Balance sheet Eicher Motors Ltd
B4: Particulars | C4: 43891 | D4: 44256 | E4: 44621 | F4: 44986 | G4: 45352 | H4: 45717
B5: Equity Capital | C5: 27 | D5: 27 | E5: 27 | F5: 27 | G5: 27 | H5: 27
B6: Reserves | C6: 9954 | D6: 11411 | E6: 12581 | F6: 14963 | G6: 18018 | H6: 21269
B7: Borrowings -
B8: Long term Borrowings | C8: 0 | D8: 0 | E8: 0 | F8: 63 | G8: 163 | H8: 184
B9: Short term Borrowings | C9: 144 | D9: 157 | E9: 59 | F9: 133 | G9: 112 | H9: 82
B10: Lease Liabilities | C10: 105 | D10: 62 | E10: 49 | F10: 93 | G10: 144 | H10: 192
B11: Current Liabilities -
B12: Trade Payables | C12: 1008 | D12: 1513 | E12: 1788 | F12: 1810 | G12: 2090 | H12: 2530
B13: Advance from Customers | C13: 61 | D13: 137 | E13: 148 | F13: 126 | G13: 0 | H13: 0
B14: Other liability items | C14: 1151 | D14: 1251 | E14: 1488 | F14: 1982 | G14: 2560 | H14: 2890
B15: Total Liabilities | C15: 12450 | D15: 14559 | E15: 16140 | F15: 19198 | G15: 23115 | H15: 27174
B17: Fixed Assets -
B18: Land | C18: 182 | D18: 232 | E18: 230 | F18: 230 | G18: 227 | H18: 226
B19: Building | C19: 871 | D19: 866 | E19: 867 | F19: 1051 | G19: 1086 | H19: 1396
B20: Plant Machinery | C20: 1928 | D20: 2088 | E20: 2336 | F20: 2598 | G20: 2744 | H20: 3055
B21: Equipments | C21: 188 | D21: 204 | E21: 226 | F21: 266 | G21: 231 | H21: 273
B22: Furniture n fittings | C22: 34 | D22: 38 | E22: 37 | F22: 39 | G22: 42 | H22: 44
B23: Vehicles | C23: 81 | D23: 97 | E23: 122 | F23: 137 | G23: 180 | H23: 224
B24: Intangible Assets | C24: 0 | D24: 0 | E24: 0 | F24: 0 | G24: 0 | H24: 0
B25: Other fixed assets | C25: 301 | D25: 523 | E25: 588 | F25: 820 | G25: 1177 | H25: 1501
B26: Gross Block | C26: 3585 | D26: 4049 | E26: 4405 | F26: 5142 | G26: 5687 | H26: 6718
B27: Accumulated Depreciation | C27: 1208 | D27: 1616 | E27: 1981 | F27: 2452 | G27: 2772 | H27: 3245
B28: Net Block (Non Current Assets) | C28: =C26-C27 -> 2377 | D28: =D26-D27 -> 2433 | E28: =E26-E27 -> 2424 | F28: =F26-F27 -> 2690 | G28: =G26-G27 -> 2915 | H28: =H26-H27 -> 3473
B30: CWIP | C30: 312 | D30: 314 | E30: 505 | F30: 472 | G30: 555 | H30: 491
B31: Investments | C31: 825 | D31: 1078 | E31: 3388 | F31: 4987 | G31: 5581 | H31: 4923
B33: Other Assets -
B34: Inventories | C34: 572 | D34: 875 | E34: 1132 | F34: 1278 | G34: 1410 | H34: 1564
B35: Trade receivables | C35: 87 | D35: 158 | E35: 302 | F35: 369 | G35: 374 | H35: 550
B36: Cash Equivalents | C36: 2951 | D36: 5830 | E36: 2722 | F36: 766 | G36: 146 | H36: 263
B37: Loans n Advances | C37: 99 | D37: 594 | E37: 867 | F37: 835 | G37: 680 | H37: 725
B38: Other asset items | C38: 303 | D38: 452 | E38: 466 | F38: 467 | G38: 3509 | H38: 5317
B39: Total Assets | C39: 12450 | D39: 14559 | E39: 16140 | F39: 19198 | G39: 23115 | H39: 27174
B43: Cash Flow Statement
C45: =C4 -> 43891 | D45: =D4 -> 44256 | E45: =E4 -> 44621 | F45: =F4 -> 44986 | G45: =G4 -> 45352 | H45: =H4 -> 45717
B47: Operating Activity -
B48: Profit from operations | C48: 2236 | D48: 1912 | E48: 2172 | F48: 3527 | G48: 4404 | H48: 4849
B49: Receivables | C49: 0 | D49: -73 | E49: -147 | F49: -59 | G49: -5 | H49: -176
B50: Inventory | C50: 61 | D50: -302 | E50: -258 | F50: -146 | G50: -131 | H50: -154
B51: Payables | C51: -235 | D51: 495 | E51: 283 | F51: 22 | G51: 304 | H51: 440
B52: Loans Advances | C52: 1 | D52: 0 | E52: 0 | F52: 0 | G52: 0 | H52: 0
B53: Other WC items | C53: 259 | D53: 115 | E53: -10 | F53: 249 | G53: 220 | H53: 101
B54: Working capital changes | C54: 86 | D54: 235 | E54: -131 | F54: 66 | G54: 388 | H54: 211
B55: Direct taxes | C55: -628 | D55: -457 | E55: -514 | F55: -770 | G55: -1068 | H55: -1080
B56: Cash from Operating Activity - | C56: =SUM(C48:C55) -> 1780 | D56: =SUM(D48:D55) -> 1925 | E56: =SUM(E48:E55) -> 1395 | F56: =SUM(F48:F55) -> 2889 | G56: =SUM(G48:G55) -> 4112 | H56: =SUM(H48:H55) -> 4191
B58: Investing Activity -
B59: Fixed assets purchased | C59: -546 | D59: -532 | E59: -641 | F59: -682 | G59: -819 | H59: -1039
B60: Fixed assets sold | C60: 1 | D60: 17 | E60: 2 | F60: 9 | G60: 4 | H60: 11
B61: Investments purchased | C61: -8746 | D61: -3983 | E61: -7134 | F61: -9103 | G61: -6106 | H61: -6939
B62: Investments sold | C62: 8176 | D62: 5971 | E62: 3500 | F62: 5080 | G62: 5968 | H62: 6826
B63: Interest received | C63: 204 | D63: 192 | E63: 398 | F63: 204 | G63: 112 | H63: 188
B64: Dividends received | C64: 68 | D64: 0 | E64: 27 | F64: 41 | G64: 95 | H64: 136
B65: Investment in group cos | C65: -1 | D65: 0 | E65: 0 | F65: 0 | G65: 0 | H65: 0
B66: Other investing items | C66: -665 | D66: -3290 | E66: 2864 | F66: 2055 | G66: -2089 | H66: -1643
B67: Cash from Investing Activity - | C67: =SUM(C59:C66) -> -1509 | D67: =SUM(D59:D66) -> -1625 | E67: =SUM(E59:E66) -> -984 | F67: =SUM(F59:F66) -> -2396 | G67: =SUM(G59:G66) -> -2835 | H67: =SUM(H59:H66) -> -2460
B69: Financing Activity -
B70: Proceeds from shares | C70: 29 | D70: 38 | E70: 6 | F70: 11 | G70: 47 | H70: 97
B71: Proceeds from borrowings | C71: 267 | D71: 40 | E71: 32 | F71: 202 | G71: 322 | H71: 38
B72: Repayment of borrowings | C72: -298 | D72: -27 | E72: -137 | F72: -20 | G72: -127 | H72: -43
B73: Interest paid fin | C73: -8 | D73: -16 | E73: -19 | F73: -18 | G73: -35 | H73: -37
B74: Dividends paid | C74: -682 | D74: 0 | E74: -465 | F74: -574 | G74: -1013 | H74: -1397
B75: Financial liabilities | C75: -40 | D75: -39 | E75: -17 | F75: -19 | G75: -37 | H75: -56
B76: Other financing items | C76: -126 | D76: -11 | E76: 5 | F76: 0 | G76: 0 | H76: 0
B77: Cash from Financing Activity - | C77: =SUM(C70:C76) -> -858 | D77: =SUM(D70:D76) -> -15 | E77: =SUM(E70:E76) -> -595 | F77: =SUM(F70:F76) -> -418 | G77: =SUM(G70:G76) -> -843 | H77: =SUM(H70:H76) -> -1398
B79: Net Cash Flow | C79: =C77+C67+C56 -> -587 | D79: =D77+D67+D56 -> 285 | E79: =E77+E67+E56 -> -184 | F79: =F77+F67+F56 -> 75 | G79: =G77+G67+G56 -> 434 | H79: =H77+H67+H56 -> 333

Sheet Ratio Analysis
B2: ="Historical Financial Statement - "&'Data Sheet'!B1&" - "&"Ratio Analysis" -> Historical Financial Statement - EICHER MOTORS LTD - Ratio Analysis
B3: Years | C3: ='Data Sheet'!B16 -> 42460 | D3: ='Data Sheet'!C16 -> 42825 | E3: ='Data Sheet'!D16 -> 43190 | F3: ='Data Sheet'!E16 -> 43555 | G3: ='Data Sheet'!F16 -> 43921 | H3: ='Data Sheet'!G16 -> 44286 | I3: ='Data Sheet'!H16 -> 44651 | J3: ='Data Sheet'!I16 -> 45016 | ... L3: ='Data Sheet'!K16 -> 45747 | M3: Trend | N3: Mean | O3: Median
B5: Sales Growth | D5: =IFERROR(HistoricalIFS!D6/HistoricalIFS!C6-1,0) -> 0.1392898 | E5: =IFERROR(HistoricalIFS!E6/HistoricalIFS!D6-1,0) -> 0.27463403 | F5: =IFERROR(HistoricalIFS!F6/HistoricalIFS!E6-1,0) -> 0.092816923 | G5: =IFERROR(HistoricalIFS!G6/HistoricalIFS!F6-1,0) -> -0.065680929 | H5: =IFERROR(HistoricalIFS!H6/HistoricalIFS!G6-1,0) -> -0.047329023 | I5: =IFERROR(HistoricalIFS!I6/HistoricalIFS!H6-1,0) -> 0.18089641 | J5: =IFERROR(HistoricalIFS!J6/HistoricalIFS!I6-1,0) -> 0.40244887 | K5: =IFERROR(HistoricalIFS!K6/HistoricalIFS!J6-1,0) -> 0.14496426 | L5: =IFERROR(HistoricalIFS!L6/HistoricalIFS!K6-1,0) -> 0.14118294 | N5: =AVERAGE(C5:L5) -> 0.14035814 | O5: =MEDIAN(C5:L5) -> 0.14118294
B6: EBITDA Growth | D6: =IFERROR(HistoricalIFS!D17/HistoricalIFS!C17-1,0) -> 0.28677954 | E6: =IFERROR(HistoricalIFS!E17/HistoricalIFS!D17-1,0) -> 0.29173393 | F6: =IFERROR(HistoricalIFS!F17/HistoricalIFS!E17-1,0) -> 0.034041508 | G6: =IFERROR(HistoricalIFS!G17/HistoricalIFS!F17-1,0) -> -0.24837823 | H6: =IFERROR(HistoricalIFS!H17/HistoricalIFS!G17-1,0) -> -0.18308756 | I6: =IFERROR(HistoricalIFS!I17/HistoricalIFS!H17-1,0) -> 0.22113805 | J6: =IFERROR(HistoricalIFS!J17/HistoricalIFS!I17-1,0) -> 0.58236934 | K6: =IFERROR(HistoricalIFS!K17/HistoricalIFS!J17-1,0) -> 0.25644858 | L6: =IFERROR(HistoricalIFS!L17/HistoricalIFS!K17-1,0) -> 0.090821528 | N6: =AVERAGE(C6:L6) -> 0.14798519 | O6: =MEDIAN(C6:L6) -> 0.22113805
B7: EBIT Growth | D7: =IFERROR(HistoricalIFS!D29/HistoricalIFS!C29-1,0) -> 0.30040425 | E7: =IFERROR(HistoricalIFS!E29/HistoricalIFS!D29-1,0) -> 0.27916051 | F7: =IFERROR(HistoricalIFS!F29/HistoricalIFS!E29-1,0) -> 0.0064496374 | G7: =IFERROR(HistoricalIFS!G29/HistoricalIFS!F29-1,0) -> -0.31354486 | H7: =IFERROR(HistoricalIFS!H29/HistoricalIFS!G29-1,0) -> -0.2616706 | I7: =IFERROR(HistoricalIFS!I29/HistoricalIFS!H29-1,0) -> 0.2969568 | J7: =IFERROR(HistoricalIFS!J29/HistoricalIFS!I29-1,0) -> 0.69404052 | K7: =IFERROR(HistoricalIFS!K29/HistoricalIFS!J29-1,0) -> 0.27300803 | L7: =IFERROR(HistoricalIFS!L29/HistoricalIFS!K29-1,0) -> 0.070094461 | N7: =AVERAGE(C7:L7) -> 0.14943319 | O7: =MEDIAN(C7:L7) -> 0.27300803
B8: Net Profit Growth | D8: =IFERROR(HistoricalIFS!D38/HistoricalIFS!C38-1,0) -> 0.28029057 | E8: =IFERROR(HistoricalIFS!E38/HistoricalIFS!D38-1,0) -> 0.27239825 | F8: =IFERROR(HistoricalIFS!F38/HistoricalIFS!E38-1,0) -> 0.018594131 | G8: =IFERROR(HistoricalIFS!G38/HistoricalIFS!F38-1,0) -> -0.17692152 | H8: =IFERROR(HistoricalIFS!H38/HistoricalIFS!G38-1,0) -> -0.26296349 | I8: =IFERROR(HistoricalIFS!I38/HistoricalIFS!H38-1,0) -> 0.24479356 | J8: =IFERROR(HistoricalIFS!J38/HistoricalIFS!I38-1,0) -> 0.73800549 | K8: =IFERROR(HistoricalIFS!K38/HistoricalIFS!J38-1,0) -> 0.37305847 | L8: =IFERROR(HistoricalIFS!L38/HistoricalIFS!K38-1,0) -> 0.18331121 | N8: =AVERAGE(C8:L8) -> 0.18561852 | O8: =MEDIAN(C8:L8) -> 0.24479356
B9: Dividend Growth | D9: =IFERROR(HistoricalIFS!D46/HistoricalIFS!C46-1,0) -> 0.0018409426 | E9: =IFERROR(HistoricalIFS!E46/HistoricalIFS!D46-1,0) -> 0.10202132 | F9: =IFERROR(HistoricalIFS!F46/HistoricalIFS!E46-1,0) -> 0.13719736 | G9: =IFERROR(HistoricalIFS!G46/HistoricalIFS!F46-1,0) -> 0.00073313783 | H9: =IFERROR(HistoricalIFS!H46/HistoricalIFS!G46-1,0) -> 0.36149451 | I9: =IFERROR(HistoricalIFS!I46/HistoricalIFS!H46-1,0) -> 0.23574611 | J9: =IFERROR(HistoricalIFS!J46/HistoricalIFS!I46-1,0) -> 0.7625492 | K9: =IFERROR(HistoricalIFS!K46/HistoricalIFS!J46-1,0) -> 0.37989031 | L9: =IFERROR(HistoricalIFS!L46/HistoricalIFS!K46-1,0) -> 0.3745542 | N9: =AVERAGE(C9:L9) -> 0.26178079 | O9: =MEDIAN(C9:L9) -> 0.23574611
B11: Gross Margin | C11: =IFERROR(HistoricalIFS!C13,0) -> 0.35112077 | D11: =IFERROR(HistoricalIFS!D13,0) -> 0.38130566 | E11: =IFERROR(HistoricalIFS!E13,0) -> 0.38850257 | F11: =IFERROR(HistoricalIFS!F13,0) -> 0.37814303 | G11: =IFERROR(HistoricalIFS!G13,0) -> 0.33207663 | H11: =IFERROR(HistoricalIFS!H13,0) -> 0.28202308 | I11: =IFERROR(HistoricalIFS!I13,0) -> 0.30394073 | J11: =IFERROR(HistoricalIFS!J13,0) -> 0.32905559 | ... L11: =IFERROR(HistoricalIFS!L13,0) -> 0.35130456 | N11: =AVERAGE(C11:L11) -> 0.34503317 | O11: =MEDIAN(C11:L11) -> 0.35121266
B12: EBITDA Margin | C12: =IFERROR(HistoricalIFS!C18,0) -> 0.27370875 | D12: =IFERROR(HistoricalIFS!D18,0) -> 0.30914243 | E12: =IFERROR(HistoricalIFS!E18,0) -> 0.31328974 | F12: =IFERROR(HistoricalIFS!F18,0) -> 0.29643995 | G12: =IFERROR(HistoricalIFS!G18,0) -> 0.23847391 | H12: =IFERROR(HistoricalIFS!H18,0) -> 0.20449065 | I12: =IFERROR(HistoricalIFS!I18,0) -> 0.21145911 | J12: =IFERROR(HistoricalIFS!J18,0) -> 0.23858725 | ... L12: =IFERROR(HistoricalIFS!L18,0) -> 0.25026404 | N12: =AVERAGE(C12:L12) -> 0.25976741 | O12: =MEDIAN(C12:L12) -> 0.25604118
B13: EBIT Margin | C13: =IFERROR(HistoricalIFS!C27,0) -> 0.25158177 | D13: =IFERROR(HistoricalIFS!D27,0) -> 0.28727379 | E13: =IFERROR(HistoricalIFS!E27,0) -> 0.28838165 | F13: =IFERROR(HistoricalIFS!F27,0) -> 0.26578994 | G13: =IFERROR(HistoricalIFS!G27,0) -> 0.19679186 | H13: =IFERROR(HistoricalIFS!H27,0) -> 0.1528035 | I13: =IFERROR(HistoricalIFS!I27,0) -> 0.16757317 | J13: =IFERROR(HistoricalIFS!J27,0) -> 0.20215161 | ... L13: =IFERROR(HistoricalIFS!L27,0) -> 0.21161452 | N13: =AVERAGE(C13:L13) -> 0.22496403 | O13: =MEDIAN(C13:L13) -> 0.21864651
B14: EBT Margin | C14: =IFERROR(HistoricalIFS!C30,0) -> 0.25123837 | D14: =IFERROR(HistoricalIFS!D30,0) -> 0.28676763 | E14: =IFERROR(HistoricalIFS!E30,0) -> 0.287786 | F14: =IFERROR(HistoricalIFS!F30,0) -> 0.26504176 | G14: =IFERROR(HistoricalIFS!G30,0) -> 0.19472928 | H14: =IFERROR(HistoricalIFS!H30,0) -> 0.15091711 | I14: =IFERROR(HistoricalIFS!I30,0) -> 0.16574948 | J14: =IFERROR(HistoricalIFS!J30,0) -> 0.20021146 | ... L14: =IFERROR(HistoricalIFS!L30,0) -> 0.20873487 | N14: =AVERAGE(C14:L14) -> 0.22337775 | O14: =MEDIAN(C14:L14) -> 0.2156682
B15: Net Profit Margin | C15: =IFERROR(HistoricalIFS!C39,0) -> 0.21674069 | D15: =IFERROR(HistoricalIFS!D39,0) -> 0.24356495 | E15: =IFERROR(HistoricalIFS!E39,0) -> 0.24313773 | F15: =IFERROR(HistoricalIFS!F39,0) -> 0.22662411 | G15: =IFERROR(HistoricalIFS!G39,0) -> 0.19964211 | H15: =IFERROR(HistoricalIFS!H39,0) -> 0.15445366 | I15: =IFERROR(HistoricalIFS!I39,0) -> 0.162811 | J15: =IFERROR(HistoricalIFS!J39,0) -> 0.20176594 | ... L15: =IFERROR(HistoricalIFS!L39,0) -> 0.25089307 | N15: =AVERAGE(C15:L15) -> 0.2141594 | O15: =MEDIAN(C15:L15) -> 0.2216824
B17: SalesExpenses%Sales | C17: =IFERROR(HistoricalIFS!C15/HistoricalIFS!C6,0) -> 0.077412019 | D17: =IFERROR(HistoricalIFS!D15/HistoricalIFS!D6,0) -> 0.072163234 | E17: =IFERROR(HistoricalIFS!E15/HistoricalIFS!E6,0) -> 0.075212829 | F17: =IFERROR(HistoricalIFS!F15/HistoricalIFS!F6,0) -> 0.081703082 | G17: =IFERROR(HistoricalIFS!G15/HistoricalIFS!G6,0) -> 0.093602722 | H17: =IFERROR(HistoricalIFS!H15/HistoricalIFS!H6,0) -> 0.077532438 | I17: =IFERROR(HistoricalIFS!I15/HistoricalIFS!I6,0) -> 0.09248162 | J17: =IFERROR(HistoricalIFS!J15/HistoricalIFS!J6,0) -> 0.090468336 | ... L17: =IFERROR(HistoricalIFS!L15/HistoricalIFS!L6,0) -> 0.10104052 | N17: =AVERAGE(C17:L17) -> 0.085265756 | O17: =MEDIAN(C17:L17) -> 0.086085709
B18: Depreciation%Sales | C18: =IFERROR(HistoricalIFS!C24,0) -> 0.022126976 | D18: =IFERROR(HistoricalIFS!D24,0) -> 0.021868637 | E18: =IFERROR(HistoricalIFS!E24,0) -> 0.024908087 | F18: =IFERROR(HistoricalIFS!F24,0) -> 0.030650011 | G18: =IFERROR(HistoricalIFS!G24,0) -> 0.041682052 | H18: =IFERROR(HistoricalIFS!H24,0) -> 0.051687146 | I18: =IFERROR(HistoricalIFS!I24,0) -> 0.043885945 | J18: =IFERROR(HistoricalIFS!J24,0) -> 0.036435635 | ... L18: =IFERROR(HistoricalIFS!L24,0) -> 0.038649522 | N18: =AVERAGE(C18:L18) -> 0.034803382 | O18: =MEDIAN(C18:L18) -> 0.036287724
B19: OperatingIncome%Sales | C19: =IFERROR(HistoricalIFS!C27,0) -> 0.25158177 | D19: =IFERROR(HistoricalIFS!D27,0) -> 0.28727379 | E19: =IFERROR(HistoricalIFS!E27,0) -> 0.28838165 | F19: =IFERROR(HistoricalIFS!F27,0) -> 0.26578994 | G19: =IFERROR(HistoricalIFS!G27,0) -> 0.19679186 | H19: =IFERROR(HistoricalIFS!H27,0) -> 0.1528035 | I19: =IFERROR(HistoricalIFS!I27,0) -> 0.16757317 | J19: =IFERROR(HistoricalIFS!J27,0) -> 0.20215161 | ... L19: =IFERROR(HistoricalIFS!L27,0) -> 0.21161452 | N19: =AVERAGE(C19:L19) -> 0.22496403 | O19: =MEDIAN(C19:L19) -> 0.21864651
B21: Return on Capital Employed | C21: =IFERROR(HistoricalIFS!C26/SUM(HistoricalIFS!C53:C55),0) -> 0.42254452 | D21: =IFERROR(HistoricalIFS!D26/SUM(HistoricalIFS!D53:D55),0) -> 0.37026381 | E21: =IFERROR(HistoricalIFS!E26/SUM(HistoricalIFS!E53:E55),0) -> 0.36002819 | F21: =IFERROR(HistoricalIFS!F26/SUM(HistoricalIFS!F53:F55),0) -> 0.28597724 | G21: =IFERROR(HistoricalIFS!G26/SUM(HistoricalIFS!G53:G55),0) -> 0.17608625 | H21: =IFERROR(HistoricalIFS!H26/SUM(HistoricalIFS!H53:H55),0) -> 0.11430576 | I21: =IFERROR(HistoricalIFS!I26/SUM(HistoricalIFS!I53:I55),0) -> 0.13570929 | J21: =IFERROR(HistoricalIFS!J26/SUM(HistoricalIFS!J53:J55),0) -> 0.19108379 | ... L21: =IFERROR(HistoricalIFS!L26/SUM(HistoricalIFS!L53:L55),0) -> 0.18355825 | N21: =AVERAGE(C21:L21) -> 0.24416571 | O21: =MEDIAN(C21:L21) -> 0.19659188
B22: Retained Earnings% | C22: =IFERROR(HistoricalIFS!C49,0) -> 0.79701653 | D22: =IFERROR(HistoricalIFS!D49,0) -> 0.84116328 | E22: =IFERROR(HistoricalIFS!E49,0) -> 0.86243187 | F22: =IFERROR(HistoricalIFS!F49,0) -> 0.84641369 | G22: =IFERROR(HistoricalIFS!G49,0) -> 0.81326336 | H22: =IFERROR(HistoricalIFS!H49,0) -> 0.65504978 | I22: =IFERROR(HistoricalIFS!I49,0) -> 0.65755696 | J22: =IFERROR(HistoricalIFS!J49,0) -> 0.65272106 | ... L22: =IFERROR(HistoricalIFS!L49,0) -> 0.59458774 | N22: =AVERAGE(C22:L22) -> 0.73711974 | O22: =MEDIAN(C22:L22) -> 0.72728675
B23: Return on Equity% | C23: =IFERROR(HistoricalIFS!C38/SUM(HistoricalIFS!C53:C54),0) -> 0.36627622 | D23: =IFERROR(HistoricalIFS!D38/SUM(HistoricalIFS!D53:D54),0) -> 0.32049721 | E23: =IFERROR(HistoricalIFS!E38/SUM(HistoricalIFS!E53:E54),0) -> 0.31005666 | F23: =IFERROR(HistoricalIFS!F38/SUM(HistoricalIFS!F53:F54),0) -> 0.24894267 | G23: =IFERROR(HistoricalIFS!G38/SUM(HistoricalIFS!G53:G54),0) -> 0.18309316 | H23: =IFERROR(HistoricalIFS!H38/SUM(HistoricalIFS!H53:H54),0) -> 0.1177549 | I23: =IFERROR(HistoricalIFS!I38/SUM(HistoricalIFS!I53:I54),0) -> 0.13297906 | J23: =IFERROR(HistoricalIFS!J38/SUM(HistoricalIFS!J53:J54),0) -> 0.19438863 | ... L23: =IFERROR(HistoricalIFS!L38/SUM(HistoricalIFS!L53:L54),0) -> 0.22231081 | N23: =AVERAGE(C23:L23) -> 0.23180168 | O23: =MEDIAN(C23:L23) -> 0.22201416
B24: Self Sustained Growth Rate | C24: =IFERROR(C22*C23,0) -> 0.2919282 | D24: =IFERROR(D22*D23,0) -> 0.26959048 | E24: =IFERROR(E22*E23,0) -> 0.26740274 | F24: =IFERROR(F22*F23,0) -> 0.21070849 | G24: =IFERROR(G22*G23,0) -> 0.14890296 | H24: =IFERROR(H22*H23,0) -> 0.077135323 | I24: =IFERROR(I22*I23,0) -> 0.087441307 | J24: =IFERROR(J22*J23,0) -> 0.12688155 | ... L24: =IFERROR(L22*L23,0) -> 0.13218328 | N24: =AVERAGE(C24:L24) -> 0.17565109 | O24: =MEDIAN(C24:L24) -> 0.14661977
B25: Interest Coverage Ratio | C25: =IFERROR(HistoricalIFS!C26/HistoricalIFS!C20,) -> 732.60849 | D25: =IFERROR(HistoricalIFS!D26/HistoricalIFS!D20,) -> 567.55618 | E25: =IFERROR(HistoricalIFS!E26/HistoricalIFS!E20,) -> 484.14419 | F25: =IFERROR(HistoricalIFS!F26/HistoricalIFS!F20,) -> 355.24693 | G25: =IFERROR(HistoricalIFS!G26/HistoricalIFS!G20,) -> 95.410487 | H25: =IFERROR(HistoricalIFS!H26/HistoricalIFS!H20,) -> 81.00304 | I25: =IFERROR(HistoricalIFS!I26/HistoricalIFS!I20,) -> 91.887114 | J25: =IFERROR(HistoricalIFS!J26/HistoricalIFS!J20,) -> 104.19379 | ... L25: =IFERROR(HistoricalIFS!L26/HistoricalIFS!L20,) -> 73.486198 | N25: =AVERAGE(C25:L25) -> 265.8881 | O25: =MEDIAN(C25:L25) -> 99.802139
B27: Debtor Turnover Ratio | C27: =IFERROR(HistoricalIFS!C65/HistoricalIFS!C6,0) -> 0.0052871485 | D27: =IFERROR(HistoricalIFS!D65/HistoricalIFS!D6,0) -> 0.007114665 | E27: =IFERROR(HistoricalIFS!E65/HistoricalIFS!E6,0) -> 0.0075850868 | F27: =IFERROR(HistoricalIFS!F65/HistoricalIFS!F6,0) -> 0.0086036015 | G27: =IFERROR(HistoricalIFS!G65/HistoricalIFS!G6,0) -> 0.0094782588 | H27: =IFERROR(HistoricalIFS!H65/HistoricalIFS!H6,0) -> 0.018136887 | I27: =IFERROR(HistoricalIFS!I65/HistoricalIFS!I6,0) -> 0.029330451 | J27: =IFERROR(HistoricalIFS!J65/HistoricalIFS!J6,0) -> 0.02554462 | ... L27: =IFERROR(HistoricalIFS!L65/HistoricalIFS!L6,0) -> 0.029127176 | N27: =AVERAGE(C27:L27) -> 0.016281221 | O27: =MEDIAN(C27:L27) -> 0.013807573
B28: Creditor Turnover Ratio | C28: =IFERROR(HistoricalIFS!C56/HistoricalIFS!C6,0) -> 0.20464213 | D28: =IFERROR(HistoricalIFS!D56/HistoricalIFS!D6,0) -> 0.22068542 | E28: =IFERROR(HistoricalIFS!E56/HistoricalIFS!E6,0) -> 0.26116346 | F28: =IFERROR(HistoricalIFS!F56/HistoricalIFS!F6,0) -> 0.23286067 | G28: =IFERROR(HistoricalIFS!G56/HistoricalIFS!G6,0) -> 0.24250512 | H28: =IFERROR(HistoricalIFS!H56/HistoricalIFS!H6,0) -> 0.33270224 | I28: =IFERROR(HistoricalIFS!I56/HistoricalIFS!I6,0) -> 0.33250889 | J28: =IFERROR(HistoricalIFS!J56/HistoricalIFS!J6,0) -> 0.27135446 | ... L28: =IFERROR(HistoricalIFS!L56/HistoricalIFS!L6,0) -> 0.28721195 | N28: =AVERAGE(C28:L28) -> 0.26668524 | O28: =MEDIAN(C28:L28) -> 0.26625896
B29: Inventory Turnover | C29: =IFERROR(HistoricalIFS!C66/HistoricalIFS!C6,0) -> 0.049954159 | D29: =IFERROR(HistoricalIFS!D66/HistoricalIFS!D6,0) -> 0.047758113 | E29: =IFERROR(HistoricalIFS!E66/HistoricalIFS!E6,0) -> 0.044020274 | F29: =IFERROR(HistoricalIFS!F66/HistoricalIFS!F6,0) -> 0.064650007 | G29: =IFERROR(HistoricalIFS!G66/HistoricalIFS!G6,0) -> 0.062527448 | H29: =IFERROR(HistoricalIFS!H66/HistoricalIFS!H6,0) -> 0.10029414 | I29: =IFERROR(HistoricalIFS!I66/HistoricalIFS!I6,0) -> 0.10996491 | J29: =IFERROR(HistoricalIFS!J66/HistoricalIFS!J6,0) -> 0.088521262 | ... L29: =IFERROR(HistoricalIFS!L66/HistoricalIFS!L6,0) -> 0.082868097 | N29: =AVERAGE(C29:L29) -> 0.073580628 | O29: =MEDIAN(C29:L29) -> 0.073759052
B30: Fixed Asset Turnover | C30: =IFERROR(HistoricalIFS!C59/HistoricalIFS!C6,0) -> 0.12790072 | D30: =IFERROR(HistoricalIFS!D59/HistoricalIFS!D6,0) -> 0.12409147 | E30: =IFERROR(HistoricalIFS!E59/HistoricalIFS!E6,0) -> 0.1675066 | F30: =IFERROR(HistoricalIFS!F59/HistoricalIFS!F6,0) -> 0.19134108 | G30: =IFERROR(HistoricalIFS!G59/HistoricalIFS!G6,0) -> 0.25973663 | H30: =IFERROR(HistoricalIFS!H59/HistoricalIFS!H6,0) -> 0.27903697 | I30: =IFERROR(HistoricalIFS!I59/HistoricalIFS!I6,0) -> 0.23541659 | J30: =IFERROR(HistoricalIFS!J59/HistoricalIFS!J6,0) -> 0.18625928 | ... L30: =IFERROR(HistoricalIFS!L59/HistoricalIFS!L6,0) -> 0.18407025 | N30: =AVERAGE(C30:L30) -> 0.19316065 | O30: =MEDIAN(C30:L30) -> 0.18516476
B31: Capital Turnover Ratio | C31: =IFERROR(SUM(HistoricalIFS!C53:C54)/HistoricalIFS!C6,0) -> 0.5917411 | D31: =IFERROR(SUM(HistoricalIFS!D53:D54)/HistoricalIFS!D6,0) -> 0.75995968 | E31: =IFERROR(SUM(HistoricalIFS!E53:E54)/HistoricalIFS!E6,0) -> 0.78417193 | F31: =IFERROR(SUM(HistoricalIFS!F53:F54)/HistoricalIFS!F6,0) -> 0.91034657 | G31: =IFERROR(SUM(HistoricalIFS!G53:G54)/HistoricalIFS!G6,0) -> 1.0903854 | H31: =IFERROR(SUM(HistoricalIFS!H53:H54)/HistoricalIFS!H6,0) -> 1.3116538 | I31: =IFERROR(SUM(HistoricalIFS!I53:I54)/HistoricalIFS!I6,0) -> 1.2243356 | J31: =IFERROR(SUM(HistoricalIFS!J53:J54)/HistoricalIFS!J6,0) -> 1.0379513 | ... L31: =IFERROR(SUM(HistoricalIFS!L53:L54)/HistoricalIFS!L6,0) -> 1.1285689 | N31: =AVERAGE(C31:L31) -> 0.99304163 | O31: =MEDIAN(C31:L31) -> 1.0641684
B33: Debtor Days | C33: =IFERROR(365/HistoricalIFS!C65,0) -> 11.182598 | D33: =IFERROR(365/HistoricalIFS!D65,0) -> 7.2941647 | E33: =IFERROR(365/HistoricalIFS!E65,0) -> 5.3676471 | F33: =IFERROR(365/HistoricalIFS!F65,0) -> 4.3302883 | G33: =IFERROR(365/HistoricalIFS!G65,0) -> 4.2070078 | H33: =IFERROR(365/HistoricalIFS!H65,0) -> 2.3077896 | I33: =IFERROR(365/HistoricalIFS!I65,0) -> 1.2084492 | J33: =IFERROR(365/HistoricalIFS!J65,0) -> 0.98937439 | ... L33: =IFERROR(365/HistoricalIFS!L65,0) -> 0.66407103 | N33: =AVERAGE(C33:L33) -> 3.85279 | O33: =MEDIAN(C33:L33) -> 3.2573987
B34: Payable Days | C34: =IFERROR(365/HistoricalIFS!C56,0) -> 0.28891439 | D34: =IFERROR(365/HistoricalIFS!D56,0) -> 0.23515617 | E34: =IFERROR(365/HistoricalIFS!E56,0) -> 0.15589497 | F34: =IFERROR(365/HistoricalIFS!F56,0) -> 0.15999299 | G34: =IFERROR(365/HistoricalIFS!G56,0) -> 0.16442997 | H34: =IFERROR(365/HistoricalIFS!H56,0) -> 0.12580654 | I34: =IFERROR(365/HistoricalIFS!I56,0) -> 0.10659673 | J34: =IFERROR(365/HistoricalIFS!J56,0) -> 0.093137192 | ... L34: =IFERROR(365/HistoricalIFS!L56,0) -> 0.067345783 | N34: =AVERAGE(C34:L34) -> 0.14757667 | O34: =MEDIAN(C34:L34) -> 0.14085075
B35: Inventory Days | C35: =IFERROR(365/HistoricalIFS!C66,0) -> 1.1835663 | D35: =IFERROR(365/HistoricalIFS!D66,0) -> 1.0866329 | E35: =IFERROR(365/HistoricalIFS!E66,0) -> 0.92489357 | F35: =IFERROR(365/HistoricalIFS!F66,0) -> 0.57627333 | G35: =IFERROR(365/HistoricalIFS!G66,0) -> 0.63772167 | H35: =IFERROR(365/HistoricalIFS!H66,0) -> 0.41733364 | I35: =IFERROR(365/HistoricalIFS!I66,0) -> 0.32232427 | J35: =IFERROR(365/HistoricalIFS!J66,0) -> 0.28550421 | ... L35: =IFERROR(365/HistoricalIFS!L66,0) -> 0.23341327 | N35: =AVERAGE(C35:L35) -> 0.59265945 | O35: =MEDIAN(C35:L35) -> 0.49680348
B36: Cash Conversion Cycle (in days) | C36: =IFERROR(365/HistoricalIFS!C67,0) -> 7.4232255 | D36: =IFERROR(365/HistoricalIFS!D67,0) -> 14.565044 | E36: =IFERROR(365/HistoricalIFS!E67,0) -> 0.30115512 | F36: =IFERROR(365/HistoricalIFS!F67,0) -> 0.12309083 | G36: =IFERROR(365/HistoricalIFS!G67,0) -> 0.12370407 | H36: =IFERROR(365/HistoricalIFS!H67,0) -> 0.062603338 | I36: =IFERROR(365/HistoricalIFS!I67,0) -> 0.13406943 | J36: =IFERROR(365/HistoricalIFS!J67,0) -> 0.47676272 | ... L36: =IFERROR(365/HistoricalIFS!L67,0) -> 1.3877799 | N36: =AVERAGE(C36:L36) -> 2.7092138 | O36: =MEDIAN(C36:L36) -> 0.38895892
B38: CFO/Sales | C38: =IFERROR(HistoricalIFS!C85/HistoricalIFS!C6,0) -> 0.2795839 | D38: =IFERROR(HistoricalIFS!D85/HistoricalIFS!D6,0) -> 0.26587577 | E38: =IFERROR(HistoricalIFS!E85/HistoricalIFS!E6,0) -> 0.3258241 | F38: =IFERROR(HistoricalIFS!F85/HistoricalIFS!F6,0) -> 0.11411587 | G38: =IFERROR(HistoricalIFS!G85/HistoricalIFS!G6,0) -> 0.19445944 | H38: =IFERROR(HistoricalIFS!H85/HistoricalIFS!H6,0) -> 0.22074802 | I38: =IFERROR(HistoricalIFS!I85/HistoricalIFS!I6,0) -> 0.13546543 | J38: =IFERROR(HistoricalIFS!J85/HistoricalIFS!J6,0) -> 0.20003905 | ... L38: =IFERROR(HistoricalIFS!L85/HistoricalIFS!L6,0) -> 0.22209445 | N38: =AVERAGE(C38:L38) -> 0.22068789 | O38: =MEDIAN(C38:L38) -> 0.22142124
B39: CFO/Total Assets | C39: =IFERROR(HistoricalIFS!C85/HistoricalIFS!C69,0) -> 0.34946275 | D39: =IFERROR(HistoricalIFS!D85/HistoricalIFS!D69,0) -> 0.26679678 | E39: =IFERROR(HistoricalIFS!E85/HistoricalIFS!E69,0) -> 0.30675588 | F39: =IFERROR(HistoricalIFS!F85/HistoricalIFS!F69,0) -> 0.098183603 | G39: =IFERROR(HistoricalIFS!G85/HistoricalIFS!G69,0) -> 0.1429751 | H39: =IFERROR(HistoricalIFS!H85/HistoricalIFS!H69,0) -> 0.13222416 | I39: =IFERROR(HistoricalIFS!I85/HistoricalIFS!I69,0) -> 0.086432137 | J39: =IFERROR(HistoricalIFS!J85/HistoricalIFS!J69,0) -> 0.15048725 | ... L39: =IFERROR(HistoricalIFS!L85/HistoricalIFS!L69,0) -> 0.15422598 | N39: =AVERAGE(C39:L39) -> 0.18654358 | O39: =MEDIAN(C39:L39) -> 0.15235661
B40: CFO/Total Debt | C40: =IFERROR(HistoricalIFS!C85/HistoricalIFS!C55,0) -> 76.473195 | D40: =IFERROR(HistoricalIFS!D85/HistoricalIFS!D55,0) -> 16.71882 | E40: =IFERROR(HistoricalIFS!E85/HistoricalIFS!E55,0) -> 19.36489 | F40: =IFERROR(HistoricalIFS!F85/HistoricalIFS!F55,0) -> 5.9862926 | G40: =IFERROR(HistoricalIFS!G85/HistoricalIFS!G55,0) -> 7.1485944 | H40: =IFERROR(HistoricalIFS!H85/HistoricalIFS!H55,0) -> 8.7799316 | I40: =IFERROR(HistoricalIFS!I85/HistoricalIFS!I55,0) -> 12.951444 | J40: =IFERROR(HistoricalIFS!J85/HistoricalIFS!J55,0) -> 10.01699 | ... L40: =IFERROR(HistoricalIFS!L85/HistoricalIFS!L55,0) -> 9.1480584 | N40: =AVERAGE(C40:L40) -> 17.639176 | O40: =MEDIAN(C40:L40) -> 9.9102686

Sheet Forcasting
B2: ='Data Sheet'!B1&" - "&'Data Sheet'!A17&" FORCASTING " -> EICHER MOTORS LTD - Sales FORCASTING | G2: ='Data Sheet'!B1&" - "&HistoricalIFS!B17&" FORCASTING " -> EICHER MOTORS LTD - EBIDTA FORCASTING | L2: ='Data Sheet'!B1&" - "&HistoricalIFS!B43&" FORCASTING " -> EICHER MOTORS LTD - Earning Per Share(EPS) FORCASTING
B3: Year Weighted | C3: Years | D3: Sales | E3: Sales Growth | G3: Year Weighted | H3: Years | I3: Sales | J3: Sales Growth | L3: Year Weighted | M3: Years | N3: Sales | O3: Sales Growth
B4: 1 | C4: =IFERROR('Data Sheet'!$B$16,0) -> 42460 | D4: {=TRANSPOSE(HistoricalIFS!C6:M6)} -> 6173.46 | G4: 1 | H4: =C4 -> 42460 | I4: {=TRANSPOSE(HistoricalIFS!C17:M17)} -> 1689.73 | L4: 1 | M4: =H4 -> 42460 | N4: {=TRANSPOSE(HistoricalIFS!C43:M43)} -> 49.265096
B5: =B4+1 -> 2 | C5: =C4+365 -> 42825 | D5: 7033.36 | E5: =IFERROR(D5/D4-1,0) -> 0.1392898 | G5: =G4+1 -> 2 | H5: =H4+365 -> 42825 | I5: 2174.31 | J5: =IFERROR(I5/I4-1,0) -> 0.28677954 | L5: =L4+1 -> 2 | M5: =M4+365 -> 42825 | N5: 62.957736 | O5: =IFERROR(N5/N4-1,0) -> 0.27793796
B6: =B5+1 -> 3 | C6: =C5+365 -> 43190 | D6: 8964.96 | E6: =IFERROR(D6/D5-1,0) -> 0.27463403 | G6: =G5+1 -> 3 | H6: =H5+365 -> 43190 | I6: 2808.63 | J6: =IFERROR(I6/I5-1,0) -> 0.29173393 | L6: =L5+1 -> 3 | M6: =M5+365 -> 43190 | N6: 79.960382 | O6: =IFERROR(N6/N5-1,0) -> 0.27006443
B7: =B6+1 -> 4 | C7: =C6+365 -> 43555 | D7: 9797.06 | E7: =IFERROR(D7/D6-1,0) -> 0.092816923 | G7: =G6+1 -> 4 | H7: =H6+365 -> 43555 | I7: 2904.24 | J7: =IFERROR(I7/I6-1,0) -> 0.034041508 | L7: =L6+1 -> 4 | M7: =M6+365 -> 43555 | N7: 81.387463 | O7: =IFERROR(N7/N6-1,0) -> 0.017847361
B8: =B7+1 -> 5 | C8: =C7+365 -> 43920 | D8: 9153.58 | E8: =IFERROR(D8/D7-1,0) -> -0.065680929 | G8: =G7+1 -> 5 | H8: =H7+365 -> 43920 | I8: 2182.89 | J8: =IFERROR(I8/I7-1,0) -> -0.24837823 | L8: =L7+1 -> 5 | M8: =M7+365 -> 43920 | N8: 66.914683 | O8: =IFERROR(N8/N7-1,0) -> -0.17782567
B9: =B8+1 -> 6 | C9: =C8+365 -> 44285 | D9: 8720.35 | E9: =IFERROR(D9/D8-1,0) -> -0.047329023 | G9: =G8+1 -> 6 | H9: =H8+365 -> 44285 | I9: 1783.23 | J9: =IFERROR(I9/I8-1,0) -> -0.18308756 | L9: =L8+1 -> 6 | M9: =M8+365 -> 44285 | N9: 49.282473 | O9: =IFERROR(N9/N8-1,0) -> -0.26350285
B10: =B9+1 -> 7 | C10: =C9+365 -> 44650 | D10: 10297.83 | E10: =IFERROR(D10/D9-1,0) -> 0.18089641 | G10: =G9+1 -> 7 | H10: =H9+365 -> 44650 | I10: 2177.57 | J10: =IFERROR(I10/I9-1,0) -> 0.22113805 | L10: =L9+1 -> 7 | M10: =M9+365 -> 44650 | N10: 61.324067 | O10: =IFERROR(N10/N9-1,0) -> 0.24433826
B11: =B10+1 -> 8 | C11: =C10+365 -> 45015 | D11: 14442.18 | E11: =IFERROR(D11/D10-1,0) -> 0.40244887 | G11: =G10+1 -> 8 | H11: =H10+365 -> 45015 | I11: 3445.72 | J11: =IFERROR(I11/I10-1,0) -> 0.58236934 | L11: =L10+1 -> 8 | M11: =M10+365 -> 45015 | N11: 106.5426 | O11: =IFERROR(N11/N10-1,0) -> 0.73737002
B12: =B11+1 -> 9 | C12: =C11+365 -> 45380 | D12: 16535.78 | E12: =IFERROR(D12/D11-1,0) -> 0.14496426 | G12: =G11+1 -> 9 | H12: =H11+365 -> 45380 | I12: 4329.37 | J12: =IFERROR(I12/I11-1,0) -> 0.25644858 | L12: =L11+1 -> 9 | M12: =M11+365 -> 45380 | N12: 146.12893 | O12: =IFERROR(N12/N11-1,0) -> 0.37155402
B13: =B12+1 -> 10 | C13: =C12+365 -> 45745 | D13: 18870.35 | E13: =IFERROR(D13/D12-1,0) -> 0.14118294 | G13: =G12+1 -> 10 | H13: =H12+365 -> 45745 | I13: 4722.57 | J13: =IFERROR(I13/I12-1,0) -> 0.090821528 | L13: =L12+1 -> 10 | M13: =M12+365 -> 45745 | N13: 172.66375 | O13: =IFERROR(N13/N12-1,0) -> 0.18158501
B14: =B13+1 -> 11 | C14: =C13+365 -> 46110 | D14: =FORECAST(B13,$D$4:$D$13,$B$4:$B$13) -> 16705.549 | E14: =IFERROR(D14/D13-1,0) -> -0.1147197 | G14: =G13+1 -> 11 | H14: =H13+365 -> 46110 | I14: =FORECAST(G13,$I$4:$I$13,$G$4:$G$13) -> 3994.1922 | J14: =IFERROR(I14/I13-1,0) -> -0.15423336 | L14: =L13+1 -> 11 | M14: =M13+365 -> 46110 | N14: =FORECAST(L13,$N$4:$N$13,$L$4:$L$13) -> 135.31203 | O14: =IFERROR(N14/N13-1,0) -> -0.21632634
B15: =B14+1 -> 12 | C15: =C14+365 -> 46475 | D15: =FORECAST(B14,$D$4:$D$13,$B$4:$B$13) -> 17973.695 | E15: =IFERROR(D15/D14-1,0) -> 0.075911677 | G15: =G14+1 -> 12 | H15: =H14+365 -> 46475 | I15: =FORECAST(G14,$I$4:$I$13,$G$4:$G$13) -> 4254.718 | J15: =IFERROR(I15/I14-1,0) -> 0.06522616 | L15: =L14+1 -> 12 | M15: =M14+365 -> 46475 | N15: =FORECAST(L14,$N$4:$N$13,$L$4:$L$13) -> 145.90521 | O15: =IFERROR(N15/N14-1,0) -> 0.07828706
B16: =B15+1 -> 13 | C16: =C15+365 -> 46840 | D16: =FORECAST(B15,$D$4:$D$13,$B$4:$B$13) -> 19241.842 | E16: =IFERROR(D16/D15-1,0) -> 0.070555677 | G16: =G15+1 -> 13 | H16: =H15+365 -> 46840 | I16: =FORECAST(G15,$I$4:$I$13,$G$4:$G$13) -> 4515.2438 | J16: =IFERROR(I16/I15-1,0) -> 0.061232218 | L16: =L15+1 -> 13 | M16: =M15+365 -> 46840 | N16: =FORECAST(L15,$N$4:$N$13,$L$4:$L$13) -> 156.49839 | O16: =IFERROR(N16/N15-1,0) -> 0.072603171
B17: =B16+1 -> 14 | C17: =C16+365 -> 47205 | D17: =FORECAST(B16,$D$4:$D$13,$B$4:$B$13) -> 20509.988 | E17: =IFERROR(D17/D16-1,0) -> 0.065905659 | G17: =G16+1 -> 14 | H17: =H16+365 -> 47205 | I17: =FORECAST(G16,$I$4:$I$13,$G$4:$G$13) -> 4775.7696 | J17: =IFERROR(I17/I16-1,0) -> 0.057699169 | L17: =L16+1 -> 14 | M17: =M16+365 -> 47205 | N17: =FORECAST(L16,$N$4:$N$13,$L$4:$L$13) -> 167.09158 | O17: =IFERROR(N17/N16-1,0) -> 0.067688753
B18: =B17+1 -> 15 | C18: =C17+365 -> 47570 | D18: =FORECAST(B17,$D$4:$D$13,$B$4:$B$13) -> 21778.134 | E18: =IFERROR(D18/D17-1,0) -> 0.061830668 | G18: =G17+1 -> 15 | H18: =H17+365 -> 47570 | I18: =FORECAST(G17,$I$4:$I$13,$G$4:$G$13) -> 5036.2955 | J18: =IFERROR(I18/I17-1,0) -> 0.054551588 | L18: =L17+1 -> 15 | M18: =M17+365 -> 47570 | N18: =FORECAST(L17,$N$4:$N$13,$L$4:$L$13) -> 177.68476 | O18: =IFERROR(N18/N17-1,0) -> 0.063397458

Sheet WACC
B1: WACC- Weighted Average Cost of Capital
B4: Peer Comparable WACC
B6: Weekly - Two Year Range
G7: Debt/ | H7: Debt / | I7: levered | J7: Unlevered
B8: Name of The comps | C8: Country | D8: Total Debt | E8: Total Equity | F8: Tax Rate 1 | G8: Equity | H8: Capital | I8: Beta 2 | J8: Beta 3
B10: Bajaj Auto | C10: India | D10: =Data!F3 -> 19693.24 | E10: =Data!E3 -> 275722.37 | F10: 0.3 | G10: =D10/E10 -> 0.071424165 | H10: =D10/(D10+E10) -> 0.066662828 | I10: 1.27 | J10: =I10/(1+(1-F10)*G10) -> 1.2095274
B11: Eicher Motors | C11: India | D11: =Data!F4 -> 445.78 | E11: =Data!E4 -> 195532.53 | F11: 0.3 | G11: =D11/E11 -> 0.0022798253 | H11: =D11/(D11+E11) -> 0.0022746395 | I11: 0.97 | J11: =I11/(1+(1-F11)*G11) -> 0.96845447
B12: TVS Motor Co. | C12: India | D12: =Data!F5 -> 31589.29 | E12: =Data!E5 -> 179587.67 | F12: 0.3 | G12: =D12/E12 -> 0.17589899 | H12: =D12/(D12+E12) -> 0.14958682 | I12: 1.4 | J12: =I12/(1+(1-F12)*G12) -> 1.2465172
B13: Hero Motocorp | C13: India | D13: =Data!F6 -> 718.07 | E13: =Data!E6 -> 105745.47 | F13: 0.3 | G13: =D13/E13 -> 0.0067905509 | H13: =D13/(D13+E13) -> 0.0067447504 | I13: 1.1 | J13: =I13/(1+(1-F13)*G13) -> 1.094796
E15: Average | F15: =AVERAGE(F10:F13) -> 0.3 | G15: =AVERAGE(G10:G13) -> 0.064098383 | H15: =AVERAGE(H10:H13) -> 0.05631726 | I15: =AVERAGE(I10:I13) -> 1.185 | J15: =AVERAGE(J10:J13) -> 1.1298238
E16: Median | F16: =MEDIAN(F10:F13) -> 0.3 | G16: =MEDIAN(G10:G13) -> 0.039107358 | H16: =MEDIAN(H10:H13) -> 0.036703789 | I16: =MEDIAN(I10:I13) -> 1.185 | J16: =MEDIAN(J10:J13) -> 1.1521617
B19: Cost of Debt | G19: Cost Of Equity
B21: Pre-Tax Cost of Debt | E21: 0.063817824 | G21: Risk Free Rate | J21: 0.0686
B22: Tax rate | E22: =F13 -> 0.3 | G22: Equity Risk Premium | J22: ='Rm calculation '!F6-WACC!J21 -> 0.095692308
B23: Post Tax Cost of Debt | E23: =E21*(1-E22) -> 0.044672477 | G23: Levered Beta 4 | J23: =J33 -> 1.2002929
G24: Cost Of Equity | J24: =J21+J22*J23 -> 0.1834588
B28: Capital Structure | G28: Levered Beta
D30: Current | E30: Target | G30: Comps Median Unlevered Beta | J30: =J16 -> 1.1521617
B31: Total Debt | C31: =D11 -> 445.78 | D31: =C31/C33 -> 0.0022746395 | E31: =H15 -> 0.05631726 | G31: Target Debt/Equity | J31: =E36 -> 0.059678171
B32: Market Capitalization | C32: =E11 -> 195532.53 | D32: =C32/C33 -> 0.99772536 | E32: =E33-E31 -> 0.94368274 | G32: Tax Rate | J32: =E22 -> 0.3
B33: Total Capital | C33: =SUM(C31:C32) -> 195978.31 | D33: =C33/C33 -> 1 | E33: =D33/D33 -> 1 | G33: Levered Beta | J33: =J30*(1+(1-J32)*J31) -> 1.2002929
B36: Debt / Equity | D36: =D31/D32 -> 0.0022798253 | E36: =E31/E32 -> 0.059678171 | G36: Weighted Average Cost of Capital
G37: Cost of Equity | J37: =J24 -> 0.1834588
G38: Equity Weight | J38: =E32 -> 0.94368274
G40: Cost of Debt | J40: =E23 -> 0.044672477
G41: Debt Weight | J41: =E31 -> 0.05631726
G42: WACC | J42: =(J37*J38)+(J40*J41) -> 0.17564273

Sheet Intrinsic Rate
B1: Intrinsic Growth Rate (IGR) Calculation
B4: Particulars | D4: ='Raw Data'!C4 -> 43891 | E4: ='Raw Data'!D4 -> 44256 | F4: ='Raw Data'!E4 -> 44621 | G4: ='Raw Data'!F4 -> 44986 | H4: ='Raw Data'!G4 -> 45352 | I4: ='Raw Data'!H4 -> 45717
A6: # | B6: Calculation of ROIC
B7: Current Assets
B8: ='Raw Data'!B34 -> Inventories | D8: ='Raw Data'!C34 -> 572 | E8: ='Raw Data'!D34 -> 875 | F8: ='Raw Data'!E34 -> 1132 | G8: ='Raw Data'!F34 -> 1278 | H8: ='Raw Data'!G34 -> 1410 | I8: ='Raw Data'!H34 -> 1564
B9: ='Raw Data'!B35 -> Trade receivables | D9: ='Raw Data'!C35 -> 87 | E9: ='Raw Data'!D35 -> 158 | F9: ='Raw Data'!E35 -> 302 | G9: ='Raw Data'!F35 -> 369 | H9: ='Raw Data'!G35 -> 374 | I9: ='Raw Data'!H35 -> 550
B10: ='Raw Data'!B37 -> Loans n Advances | D10: ='Raw Data'!C37 -> 99 | E10: ='Raw Data'!D37 -> 594 | F10: ='Raw Data'!E37 -> 867 | G10: ='Raw Data'!F37 -> 835 | H10: ='Raw Data'!G37 -> 680 | I10: ='Raw Data'!H37 -> 725
B11: ='Raw Data'!B38 -> Other asset items | D11: ='Raw Data'!C38 -> 303 | E11: ='Raw Data'!D38 -> 452 | F11: ='Raw Data'!E38 -> 466 | G11: ='Raw Data'!F38 -> 467 | H11: ='Raw Data'!G38 -> 3509 | I11: ='Raw Data'!H38 -> 5317
B12: Total Current Assets | D12: =SUM(D8:D11) -> 1061 | E12: =SUM(E8:E11) -> 2079 | F12: =SUM(F8:F11) -> 2767 | G12: =SUM(G8:G11) -> 2949 | H12: =SUM(H8:H11) -> 5973 | I12: =SUM(I8:I11) -> 8156
B14: Current Liblities
B15: ='Raw Data'!B12 -> Trade Payables | D15: ='Raw Data'!C12 -> 1008 | E15: ='Raw Data'!D12 -> 1513 | F15: ='Raw Data'!E12 -> 1788 | G15: ='Raw Data'!F12 -> 1810 | H15: ='Raw Data'!G12 -> 2090 | I15: ='Raw Data'!H12 -> 2530
B16: ='Raw Data'!B13 -> Advance from Customers | D16: ='Raw Data'!C13 -> 61 | E16: ='Raw Data'!D13 -> 137 | F16: ='Raw Data'!E13 -> 148 | G16: ='Raw Data'!F13 -> 126 | H16: ='Raw Data'!G13 -> 0 | I16: ='Raw Data'!H13 -> 0
B17: ='Raw Data'!B14 -> Other liability items | D17: ='Raw Data'!C14 -> 1151 | E17: ='Raw Data'!D14 -> 1251 | F17: ='Raw Data'!E14 -> 1488 | G17: ='Raw Data'!F14 -> 1982 | H17: ='Raw Data'!G14 -> 2560 | I17: ='Raw Data'!H14 -> 2890
B18: Total Current Assets | D18: =SUM(D15:D17) -> 2220 | E18: =SUM(E15:E17) -> 2901 | F18: =SUM(F15:F17) -> 3424 | G18: =SUM(G15:G17) -> 3918 | H18: =SUM(H15:H17) -> 4650 | I18: =SUM(I15:I17) -> 5420
A20: # | B20: Net Working Capital | D20: =D12-D18 -> -1159 | E20: =E12-E18 -> -822 | F20: =F12-F18 -> -657 | G20: =G12-G18 -> -969 | H20: =H12-H18 -> 1323 | I20: =I12-I18 -> 2736
B23: ='Raw Data'!B17 -> Fixed Assets -
B24: ='Raw Data'!B18 -> Land | D24: ='Raw Data'!C18 -> 182 | E24: ='Raw Data'!D18 -> 232 | F24: ='Raw Data'!E18 -> 230 | G24: ='Raw Data'!F18 -> 230 | H24: ='Raw Data'!G18 -> 227 | I24: ='Raw Data'!H18 -> 226
B25: ='Raw Data'!B19 -> Building | D25: ='Raw Data'!C19 -> 871 | E25: ='Raw Data'!D19 -> 866 | F25: ='Raw Data'!E19 -> 867 | G25: ='Raw Data'!F19 -> 1051 | H25: ='Raw Data'!G19 -> 1086 | I25: ='Raw Data'!H19 -> 1396
B26: ='Raw Data'!B20 -> Plant Machinery | D26: ='Raw Data'!C20 -> 1928 | E26: ='Raw Data'!D20 -> 2088 | F26: ='Raw Data'!E20 -> 2336 | G26: ='Raw Data'!F20 -> 2598 | H26: ='Raw Data'!G20 -> 2744 | I26: ='Raw Data'!H20 -> 3055
B27: ='Raw Data'!B21 -> Equipments | D27: ='Raw Data'!C21 -> 188 | E27: ='Raw Data'!D21 -> 204 | F27: ='Raw Data'!E21 -> 226 | G27: ='Raw Data'!F21 -> 266 | H27: ='Raw Data'!G21 -> 231 | I27: ='Raw Data'!H21 -> 273
B28: ='Raw Data'!B22 -> Furniture n fittings | D28: ='Raw Data'!C22 -> 34 | E28: ='Raw Data'!D22 -> 38 | F28: ='Raw Data'!E22 -> 37 | G28: ='Raw Data'!F22 -> 39 | H28: ='Raw Data'!G22 -> 42 | I28: ='Raw Data'!H22 -> 44
B29: ='Raw Data'!B23 -> Vehicles | D29: ='Raw Data'!C23 -> 81 | E29: ='Raw Data'!D23 -> 97 | F29: ='Raw Data'!E23 -> 122 | G29: ='Raw Data'!F23 -> 137 | H29: ='Raw Data'!G23 -> 180 | I29: ='Raw Data'!H23 -> 224
B30: ='Raw Data'!B24 -> Intangible Assets | D30: ='Raw Data'!C24 -> 0 | E30: ='Raw Data'!D24 -> 0 | F30: ='Raw Data'!E24 -> 0 | G30: ='Raw Data'!F24 -> 0 | H30: ='Raw Data'!G24 -> 0 | I30: ='Raw Data'!H24 -> 0
B31: ='Raw Data'!B25 -> Other fixed assets | D31: ='Raw Data'!C25 -> 301 | E31: ='Raw Data'!D25 -> 523 | F31: ='Raw Data'!E25 -> 588 | G31: ='Raw Data'!F25 -> 820 | H31: ='Raw Data'!G25 -> 1177 | I31: ='Raw Data'!H25 -> 1501
B32: Gross Block | D32: =SUM(D24:D31) -> 3585 | E32: =SUM(E24:E31) -> 4048 | F32: =SUM(F24:F31) -> 4406 | G32: =SUM(G24:G31) -> 5141 | H32: =SUM(H24:H31) -> 5687 | I32: =SUM(I24:I31) -> 6719
B33: ='Raw Data'!B27 -> Accumulated Depreciation | D33: =-'Raw Data'!C27 -> -1208 | E33: =-'Raw Data'!D27 -> -1616 | F33: =-'Raw Data'!E27 -> -1981 | G33: =-'Raw Data'!F27 -> -2452 | H33: =-'Raw Data'!G27 -> -2772 | I33: =-'Raw Data'!H27 -> -3245
B34: Net Non - Current Assets | D34: =SUM(D32:D33) -> 2377 | E34: =SUM(E32:E33) -> 2432 | F34: =SUM(F32:F33) -> 2425 | G34: =SUM(G32:G33) -> 2689 | H34: =SUM(H32:H33) -> 2915 | I34: =SUM(I32:I33) -> 3474
A36: # | B36: Invested Capital | D36: =D34+D20 -> 1218 | E36: =E34+E20 -> 1610 | F36: =F34+F20 -> 1768 | G36: =G34+G20 -> 1720 | H36: =H34+H20 -> 4238 | I36: =I34+I20 -> 6210
B37: EBIT | D37: =HistoricalIFS!G26 -> 1801.35 | E37: =HistoricalIFS!H26 -> 1332.5 | F37: =HistoricalIFS!I26 -> 1725.64 | G37: =HistoricalIFS!J26 -> 2919.51 | H37: =HistoricalIFS!K26 -> 3731.77 | I37: =HistoricalIFS!L26 -> 3993.24
A39: # | B39: ROIC | D39: =D37/D36 -> 1.4789409 | E39: =E37/E36 -> 0.82763975 | F39: =F37/F36 -> 0.97604072 | G39: =G37/G36 -> 1.6973895 | H39: =H37/H36 -> 0.88054979 | I39: =I37/I36 -> 0.64303382
A41: # | B41: Calculation Reinvetment Rate
B43: Capital Expenditure
B44: ='Raw Data'!B59 -> Fixed assets purchased | D44: ='Raw Data'!C59 -> -546 | E44: ='Raw Data'!D59 -> -532 | F44: ='Raw Data'!E59 -> -641 | G44: ='Raw Data'!F59 -> -682 | H44: ='Raw Data'!G59 -> -819 | I44: ='Raw Data'!H59 -> -1039
B45: ='Raw Data'!B60 -> Fixed assets sold | D45: ='Raw Data'!C60 -> 1 | E45: ='Raw Data'!D60 -> 17 | F45: ='Raw Data'!E60 -> 2 | G45: ='Raw Data'!F60 -> 9 | H45: ='Raw Data'!G60 -> 4 | I45: ='Raw Data'!H60 -> 11
B46: Net Capex | D46: =-SUM(D44:D45) -> 545 | E46: =-SUM(E44:E45) -> 515 | F46: =-SUM(F44:F45) -> 639 | G46: =-SUM(G44:G45) -> 673 | H46: =-SUM(H44:H45) -> 815 | I46: =-SUM(I44:I45) -> 1028
B47: Change in Working Capital | E47: =E20-D20 -> 337 | F47: =F20-E20 -> 165 | G47: =G20-F20 -> -312 | H47: =H20-G20 -> 2292 | I47: =I20-H20 -> 1413
B49: EBIT | D49: =D37 -> 1801.35 | E49: =E37 -> 1332.5 | F49: =F37 -> 1725.64 | G49: =G37 -> 2919.51 | H49: =H37 -> 3731.77 | I49: =I37 -> 3993.24
B50: Marginal Rate | D50: 0.25 | E50: 0.25 | F50: 0.25 | G50: 0.25 | H50: 0.25 | I50: 0.25
B51: EBIT(1-Tax) | D51: =D49*(1-D50) -> 1351.0125 | E51: =E49*(1-E50) -> 999.375 | F51: =F49*(1-F50) -> 1294.23 | G51: =G49*(1-G50) -> 2189.6325 | H51: =H49*(1-H50) -> 2798.8275 | I51: =I49*(1-I50) -> 2994.93
A53: # | B53: Reinvestment Amount | E53: =SUM(E46:E47) -> 852 | F53: =SUM(F46:F47) -> 804 | G53: =SUM(G46:G47) -> 361 | H53: =SUM(H46:H47) -> 3107 | I53: =SUM(I46:I47) -> 2441
A55: # | B55: Reinvestment Rate | E55: =E53/E51 -> 0.85253283 | F55: =F53/F51 -> 0.62121879 | G55: =G53/G51 -> 0.16486785 | H55: =H53/H51 -> 1.1101077 | I55: =I53/I51 -> 0.81504409
G57: 4 Year Avereage | I57: =AVERAGE(E55:I55) -> 0.71275426
G58: 4 Years Median | I58: =MEDIAN(E55:I55) -> 0.81504409
A60: # | B60: Calculation Of Growth Rate
B62: =B39 -> ROIC | D62: =D39 -> 1.4789409 | E62: =E39 -> 0.82763975 | F62: =F39 -> 0.97604072 | G62: =G39 -> 1.6973895 | H62: =H39 -> 0.88054979 | I62: =I39 -> 0.64303382
B63: =B55 -> Reinvestment Rate | D63: - | E63: =E55 -> 0.85253283 | F63: =F55 -> 0.62121879 | G63: =G55 -> 0.16486785 | H63: =H55 -> 1.1101077 | I63: =I55 -> 0.81504409
A65: # | B65: Intrinsic Growth Rate | E65: =E62*E63 -> 0.70559006 | F65: =F62*F63 -> 0.60633484 | G65: =G62*G63 -> 0.27984496 | H65: =H62*H63 -> 0.97750511 | I65: =I62*I63 -> 0.52410091
G67: 4 Year Avereage | I67: =AVERAGE(E65:I65) -> 0.61867518
G68: 4 Years Median | I68: =MEDIAN(E65:I65) -> 0.60633484

Sheet Equity valuation
B1: EQUITY VALUVATION
A4: # | B4: Calculation of PV of Future Cashflow
B6: Particulars | C6: ='Intrinsic Rate'!D4 -> 43891 | D6: ='Intrinsic Rate'!E4 -> 44256 | E6: ='Intrinsic Rate'!F4 -> 44621 | F6: ='Intrinsic Rate'!G4 -> 44986 | G6: ='Intrinsic Rate'!H4 -> 45352 | H6: ='Intrinsic Rate'!I4 -> 45717
B7: EBIT | C7: =HistoricalIFS!G26 -> 1801.35 | D7: =HistoricalIFS!H26 -> 1332.5 | E7: =HistoricalIFS!I26 -> 1725.64 | F7: =HistoricalIFS!J26 -> 2919.51 | G7: =HistoricalIFS!K26 -> 3731.77 | H7: =HistoricalIFS!L26 -> 3993.24
B8: Tax Rate | C8: 0.25 | D8: 0.25 | E8: 0.25 | F8: 0.25 | G8: 0.25 | H8: 0.25
B9: EBIT*(1-Tax Rate) | C9: =C7*(1-C8) -> 1351.0125 | D9: =D7*(1-D8) -> 999.375 | E9: =E7*(1-E8) -> 1294.23 | F9: =F7*(1-F8) -> 2189.6325 | G9: =G7*(1-G8) -> 2798.8275 | H9: =H7*(1-H8) -> 2994.93
B10: Reinvested Rate | C10: ='Intrinsic Rate'!I58 -> 0.81504409 | D10: =C10+(($H$10-$C$10)/4) -> 0.82503307 | E10: =D10+(($H$10-$C$10)/4) -> 0.83502205 | F10: =E10+(($H$10-$C$10)/4) -> 0.84501102 | G10: =F10+(($H$10-$C$10)/4) -> 0.855 | H10: 0.855
B11: FCFF | C11: =C9*(1-C10) -> 249.87774 | D11: =D9*(1-D10) -> 174.85758 | E11: =E9*(1-E10) -> 213.51942 | F11: =F9*(1-F10) -> 339.3689 | G11: =G9*(1-G10) -> 405.82999 | H11: =H9*(1-H10) -> 434.26485
B12: Mid Year Convention | D12: 0.5 | E12: =D12+1 -> 1.5 | F12: =E12+1 -> 2.5 | G12: =F12+1 -> 3.5 | H12: =G12+1 -> 4.5
B13: Discounted Factors | D13: =1/(1+$C$19)^D12 -> 0.922279 | E13: =1/(1+$C$19)^E12 -> 0.78448917 | F13: =1/(1+$C$19)^F12 -> 0.66728535 | G13: =1/(1+$C$19)^G12 -> 0.56759195 | H13: =1/(1+$C$19)^H12 -> 0.48279289
B14: PV of Future CashFlow | D14: =D11*D13 -> 161.26747 | E14: =E11*E13 -> 167.50367 | F14: =F11*F13 -> 226.4559 | G14: =G11*G13 -> 230.34583 | H14: =H11*H13 -> 209.65998
B17: Expected Growth | C17: ='Intrinsic Rate'!I68 -> 0.60633484
B18: Terminal Growth | C18: 0.0538
B19: WACC | C19: =WACC!J42 -> 0.17564273
A22: # | B22: Calculation of Terminal Value
B24: FCFF (n+1) | C24: =H11*(1-H10) -> 62.968403
B25: WACC | C25: =C19 -> 0.17564273
B26: Terminal Growth Rate | C26: =C18 -> 0.0538
B27: Terminal Value | C27: =C24/(C25-C26) -> 516.80064
A30: # | B30: Calculation of Equity Value per Share
B32: PV of FCFF | C32: =SUM(D14:H14) -> 995.23285
B33: PV of Terminal Value | C33: =C27*H13 -> 249.50767
B34: Value of Operating Assets | C34: =SUM(C32:C33) -> 1244.7405
B36: Add: Cash | C36: ='Raw Data'!H36 -> 263
B37: Less: Debt | C37: =SUM('Raw Data'!H8:H9) -> 266
B38: Value of Equity | C38: =C34+C36-C37 -> 1241.7405
B39: No of Shares | C39: ='Data Sheet'!B6 -> 27.431004
A41: # | B41: Share Price Value | C41: =C38/C39 -> 45.267775
B43: Share price | C43: 7190
B44: Discount/Premium | C44: =C43/C41 -> 158.83263

Sheet HistoricalIFS
B2: ="Historical Financial Statement - "&'Data Sheet'!B1 -> Historical Financial Statement - EICHER MOTORS LTD
B3: Years | C3: ='Data Sheet'!B16 -> 42460 | D3: ='Data Sheet'!C16 -> 42825 | E3: ='Data Sheet'!D16 -> 43190 | F3: ='Data Sheet'!E16 -> 43555 | G3: ='Data Sheet'!F16 -> 43921 | H3: ='Data Sheet'!G16 -> 44286 | I3: ='Data Sheet'!H16 -> 44651 | J3: ='Data Sheet'!I16 -> 45016 | ... L3: ='Data Sheet'!K16 -> 45747 | M3: LTM
A5: # | B5: Income Statement
B6: Sales | C6: =IFERROR('Data Sheet'!B17,0) -> 6173.46 | D6: =IFERROR('Data Sheet'!C17,0) -> 7033.36 | E6: =IFERROR('Data Sheet'!D17,0) -> 8964.96 | F6: =IFERROR('Data Sheet'!E17,0) -> 9797.06 | G6: =IFERROR('Data Sheet'!F17,0) -> 9153.58 | H6: =IFERROR('Data Sheet'!G17,0) -> 8720.35 | I6: =IFERROR('Data Sheet'!H17,0) -> 10297.83 | J6: =IFERROR('Data Sheet'!I17,0) -> 14442.18 | ... L6: =IFERROR('Data Sheet'!K17,0) -> 18870.35 | M6: =IFERROR(SUM('Data Sheet'!H42:K42),0) -> 22568.58
B7: Sales Growth | C7: - | D7: =D6/C6-1 -> 0.1392898 | E7: =E6/D6-1 -> 0.27463403 | F7: =F6/E6-1 -> 0.092816923 | G7: =G6/F6-1 -> -0.065680929 | H7: =H6/G6-1 -> -0.047329023 | I7: =I6/H6-1 -> 0.18089641 | J7: =J6/I6-1 -> 0.40244887 | K7: =K6/J6-1 -> 0.14496426 | ... M7: =M6/L6-1 -> 0.195981
B9: COGS | C9: =IFERROR(SUM('Data Sheet'!B18,'Data Sheet'!B20:B22)-1*'Data Sheet'!B19,0) -> 4005.83 | D9: =IFERROR(SUM('Data Sheet'!C18,'Data Sheet'!C20:C22)-1*'Data Sheet'!C19,0) -> 4351.5 | E9: =IFERROR(SUM('Data Sheet'!D18,'Data Sheet'!D20:D22)-1*'Data Sheet'!D19,0) -> 5482.05 | F9: =IFERROR(SUM('Data Sheet'!E18,'Data Sheet'!E20:E22)-1*'Data Sheet'!E19,0) -> 6092.37 | G9: =IFERROR(SUM('Data Sheet'!F18,'Data Sheet'!F20:F22)-1*'Data Sheet'!F19,0) -> 6113.89 | H9: =IFERROR(SUM('Data Sheet'!G18,'Data Sheet'!G20:G22)-1*'Data Sheet'!G19,0) -> 6261.01 | I9: =IFERROR(SUM('Data Sheet'!H18,'Data Sheet'!H20:H22)-1*'Data Sheet'!H19,0) -> 7167.9 | J9: =IFERROR(SUM('Data Sheet'!I18,'Data Sheet'!I20:I22)-1*'Data Sheet'!I19,0) -> 9689.9 | ... L9: =IFERROR(SUM('Data Sheet'!K18,'Data Sheet'!K20:K22)-1*'Data Sheet'!K19,0) -> 12241.11 | M9: =IFERROR(SUM('Data Sheet'!H43:K43),0) -> 17039.49
B10: COGS %of Sales | C10: =C9/C6 -> 0.64887923 | D10: =D9/D6 -> 0.61869434 | E10: =E9/E6 -> 0.61149743 | F10: =F9/F6 -> 0.62185697 | G10: =G9/G6 -> 0.66792337 | H10: =H9/H6 -> 0.71797692 | I10: =I9/I6 -> 0.69605927 | J10: =J9/J6 -> 0.67094441 | ... M10: =M9/M6 -> 0.7550094
B12: Gross Profit | C12: =C6-C9 -> 2167.63 | D12: =D6-D9 -> 2681.86 | E12: =E6-E9 -> 3482.91 | F12: =F6-F9 -> 3704.69 | G12: =G6-G9 -> 3039.69 | H12: =H6-H9 -> 2459.34 | I12: =I6-I9 -> 3129.93 | J12: =J6-J9 -> 4752.28 | ... M12: =M6-M9 -> 5529.09
B13: Gross Margin | C13: =C12/C6 -> 0.35112077 | D13: =D12/D6 -> 0.38130566 | E13: =E12/E6 -> 0.38850257 | F13: =F12/F6 -> 0.37814303 | G13: =G12/G6 -> 0.33207663 | H13: =H12/H6 -> 0.28202308 | I13: =I12/I6 -> 0.30394073 | J13: =J12/J6 -> 0.32905559 | ... M13: =M12/M6 -> 0.2449906
B15: Selling & General Expenses | C15: =IFERROR(SUM('Data Sheet'!B23:B24),0) -> 477.9 | D15: =IFERROR(SUM('Data Sheet'!C23:C24),0) -> 507.55 | E15: =IFERROR(SUM('Data Sheet'!D23:D24),0) -> 674.28 | F15: =IFERROR(SUM('Data Sheet'!E23:E24),0) -> 800.45 | G15: =IFERROR(SUM('Data Sheet'!F23:F24),0) -> 856.8 | H15: =IFERROR(SUM('Data Sheet'!G23:G24),0) -> 676.11 | I15: =IFERROR(SUM('Data Sheet'!H23:H24),0) -> 952.36 | J15: =IFERROR(SUM('Data Sheet'!I23:I24),0) -> 1306.56 | ... M15: =IFERROR(SUM('Data Sheet'!L23:L24),0) -> 0
B17: EBIDTA | C17: =C12-C15 -> 1689.73 | D17: =D12-D15 -> 2174.31 | E17: =E12-E15 -> 2808.63 | F17: =F12-F15 -> 2904.24 | G17: =G12-G15 -> 2182.89 | H17: =H12-H15 -> 1783.23 | I17: =I12-I15 -> 2177.57 | J17: =J12-J15 -> 3445.72 | ... M17: =M12-M15 -> 5529.09
B18: EBIDTA Margin | C18: =C17/C6 -> 0.27370875 | D18: =D17/D6 -> 0.30914243 | E18: =E17/E6 -> 0.31328974 | F18: =F17/F6 -> 0.29643995 | G18: =G17/G6 -> 0.23847391 | H18: =H17/H6 -> 0.20449065 | I18: =I17/I6 -> 0.21145911 | J18: =J17/J6 -> 0.23858725 | ... M18: =M17/M6 -> 0.2449906
B20: Intreste | C20: =IFERROR('Data Sheet'!B27,0) -> 2.12 | D20: =IFERROR('Data Sheet'!C27,0) -> 3.56 | E20: =IFERROR('Data Sheet'!D27,0) -> 5.34 | F20: =IFERROR('Data Sheet'!E27,0) -> 7.33 | G20: =IFERROR('Data Sheet'!F27,0) -> 18.88 | H20: =IFERROR('Data Sheet'!G27,0) -> 16.45 | I20: =IFERROR('Data Sheet'!H27,0) -> 18.78 | J20: =IFERROR('Data Sheet'!I27,0) -> 28.02 | ... L20: =IFERROR('Data Sheet'!K27,0) -> 54.34 | M20: =IFERROR(SUM('Data Sheet'!H46:K46),0) -> 66.87
B21: Intreste%of sales | C21: =C20/C6 -> 0.00034340548 | D21: =D20/D6 -> 0.00050615922 | E21: =E20/E6 -> 0.00059565241 | F21: =F20/F6 -> 0.00074818364 | G21: =G20/G6 -> 0.002062581 | H21: =H20/H6 -> 0.0018863922 | I21: =I20/I6 -> 0.0018236852 | J21: =J20/J6 -> 0.0019401503 | ... M21: =M20/M6 -> 0.0029629689
B23: Depreciation | C23: =IFERROR('Data Sheet'!B26,0) -> 136.6 | D23: =IFERROR('Data Sheet'!C26,0) -> 153.81 | E23: =IFERROR('Data Sheet'!D26,0) -> 223.3 | F23: =IFERROR('Data Sheet'!E26,0) -> 300.28 | G23: =IFERROR('Data Sheet'!F26,0) -> 381.54 | H23: =IFERROR('Data Sheet'!G26,0) -> 450.73 | I23: =IFERROR('Data Sheet'!H26,0) -> 451.93 | J23: =IFERROR('Data Sheet'!I26,0) -> 526.21 | ... L23: =IFERROR('Data Sheet'!K26,0) -> 729.33 | M23: =IFERROR(SUM('Data Sheet'!H45:K45),0) -> 810.09
B24: Depreciation%of sales | C24: =C23/C6 -> 0.022126976 | D24: =D23/D6 -> 0.021868637 | E24: =E23/E6 -> 0.024908087 | F24: =F23/F6 -> 0.030650011 | G24: =G23/G6 -> 0.041682052 | H24: =H23/H6 -> 0.051687146 | I24: =I23/I6 -> 0.043885945 | J24: =J23/J6 -> 0.036435635 | ... M24: =M23/M6 -> 0.035894593
B26: Earning Before Intreste and Tax | C26: =IFERROR(C17-C23,0) -> 1553.13 | D26: =IFERROR(D17-D23,0) -> 2020.5 | E26: =IFERROR(E17-E23,0) -> 2585.33 | F26: =IFERROR(F17-F23,0) -> 2603.96 | G26: =IFERROR(G17-G23,0) -> 1801.35 | H26: =IFERROR(H17-H23,0) -> 1332.5 | I26: =IFERROR(I17-I23,0) -> 1725.64 | J26: =IFERROR(J17-J23,0) -> 2919.51 | ... M26: =IFERROR(M17-M23,0) -> 4719
B27: EBIT % OF SALES | C27: =IFERROR(C26/C6,0) -> 0.25158177 | D27: =IFERROR(D26/D6,0) -> 0.28727379 | E27: =IFERROR(E26/E6,0) -> 0.28838165 | F27: =IFERROR(F26/F6,0) -> 0.26578994 | G27: =IFERROR(G26/G6,0) -> 0.19679186 | H27: =IFERROR(H26/H6,0) -> 0.1528035 | I27: =IFERROR(I26/I6,0) -> 0.16757317 | J27: =IFERROR(J26/J6,0) -> 0.20215161 | ... M27: =IFERROR(M26/M6,0) -> 0.20909601
B29: Earing Before Tax | C29: =C17-SUM(C20,C23) -> 1551.01 | D29: =D17-SUM(D20,D23) -> 2016.94 | E29: =E17-SUM(E20,E23) -> 2579.99 | F29: =F17-SUM(F20,F23) -> 2596.63 | G29: =G17-SUM(G20,G23) -> 1782.47 | H29: =H17-SUM(H20,H23) -> 1316.05 | I29: =I17-SUM(I20,I23) -> 1706.86 | J29: =J17-SUM(J20,J23) -> 2891.49 | ... M29: =M17-SUM(M20,M23) -> 4652.13
B30: EBT % of sales | C30: =C29/C6 -> 0.25123837 | D30: =D29/D6 -> 0.28676763 | E30: =E29/E6 -> 0.287786 | F30: =F29/F6 -> 0.26504176 | G30: =G29/G6 -> 0.19472928 | H30: =H29/H6 -> 0.15091711 | I30: =I29/I6 -> 0.16574948 | J30: =J29/J6 -> 0.20021146 | ... M30: =M29/M6 -> 0.20613304
B32: Other Income | C32: =IFERROR('Data Sheet'!B25,0) -> 325.91 | D32: =IFERROR('Data Sheet'!C25,0) -> 416.44 | E32: =IFERROR('Data Sheet'!D25,0) -> 535.66 | F32: =IFERROR('Data Sheet'!E25,0) -> 700.66 | G32: =IFERROR('Data Sheet'!F25,0) -> 572.42 | H32: =IFERROR('Data Sheet'!G25,0) -> 482.34 | I32: =IFERROR('Data Sheet'!H25,0) -> 495.65 | J32: =IFERROR('Data Sheet'!I25,0) -> 908.14 | ... L32: =IFERROR('Data Sheet'!K25,0) -> 1994.17 | M32: =IFERROR(SUM('Data Sheet'!H44:K44),0) -> 2182.23
B33: Other Income % Of sales | C33: =C32/C6 -> 0.052792113 | D33: =D32/D6 -> 0.059209254 | E33: =E32/E6 -> 0.059750406 | F33: =F32/F6 -> 0.071517374 | G33: =G32/G6 -> 0.062535096 | H33: =H32/H6 -> 0.055312 | I33: =I32/I6 -> 0.0481315 | J33: =J32/J6 -> 0.062881089 | ... M33: =M32/M6 -> 0.096693279
B35: Tax | C35: =IFERROR('Data Sheet'!B29,0) -> 538.88 | D35: =IFERROR('Data Sheet'!C29,0) -> 720.3 | E35: =IFERROR('Data Sheet'!D29,0) -> 935.93 | F35: =IFERROR('Data Sheet'!E29,0) -> 1077.04 | G35: =IFERROR('Data Sheet'!F29,0) -> 527.45 | H35: =IFERROR('Data Sheet'!G29,0) -> 451.5 | I35: =IFERROR('Data Sheet'!H29,0) -> 525.91 | J35: =IFERROR('Data Sheet'!I29,0) -> 885.69 | ... L35: =IFERROR('Data Sheet'!K29,0) -> 1198.63 | M35: =IFERROR(SUM('Data Sheet'!H48:K48),0) -> 1476.93
B36: Effective Tax Rate | C36: =C35/SUM(C29,C32) -> 0.28710867 | D36: =D35/SUM(D29,D32) -> 0.29600802 | E36: =E35/SUM(E29,E32) -> 0.30039639 | F36: =F35/SUM(F29,F32) -> 0.326644 | G36: =G35/SUM(G29,G32) -> 0.22398074 | H36: =H35/SUM(H29,H32) -> 0.25105789 | I36: =I35/SUM(I29,I32) -> 0.23877758 | J36: =J35/SUM(J29,J32) -> 0.23309901 | ... M36: =M35/SUM(M29,M32) -> 0.21610363
B38: Net Profit (PAT) | C38: =SUM(C29,C32)-C35 -> 1338.04 | D38: =SUM(D29,D32)-D35 -> 1713.08 | E38: =SUM(E29,E32)-E35 -> 2179.72 | F38: =SUM(F29,F32)-F35 -> 2220.25 | G38: =SUM(G29,G32)-G35 -> 1827.44 | H38: =SUM(H29,H32)-H35 -> 1346.89 | I38: =SUM(I29,I32)-I35 -> 1676.6 | J38: =SUM(J29,J32)-J35 -> 2913.94 | ... M38: =SUM(M29,M32)-M35 -> 5357.43
B39: Net Profit %of Sales | C39: =C38/C6 -> 0.21674069 | D39: =D38/D6 -> 0.24356495 | E39: =E38/E6 -> 0.24313773 | F39: =F38/F6 -> 0.22662411 | G39: =G38/G6 -> 0.19964211 | H39: =H38/H6 -> 0.15445366 | I39: =I38/I6 -> 0.162811 | J39: =J38/J6 -> 0.20176594 | ... M39: =M38/M6 -> 0.23738445
B41: No of Equity Shares | C41: =IFERROR('Data Sheet'!B93,0) -> 27.16 | D41: =IFERROR('Data Sheet'!C93,0) -> 27.21 | E41: =IFERROR('Data Sheet'!D93,0) -> 27.26 | F41: =IFERROR('Data Sheet'!E93,0) -> 27.28 | G41: =IFERROR('Data Sheet'!F93,0) -> 27.31 | H41: =IFERROR('Data Sheet'!G93,0) -> 27.33 | I41: =IFERROR('Data Sheet'!H93,0) -> 27.34 | J41: =IFERROR('Data Sheet'!I93,0) -> 27.35 | ... M41: =IFERROR('Data Sheet'!L93,0) -> 0
B43: Earning Per Share(EPS) | C43: =IFERROR(C38/C41,0) -> 49.265096 | D43: =IFERROR(D38/D41,0) -> 62.957736 | E43: =IFERROR(E38/E41,0) -> 79.960382 | F43: =IFERROR(F38/F41,0) -> 81.387463 | G43: =IFERROR(G38/G41,0) -> 66.914683 | H43: =IFERROR(H38/H41,0) -> 49.282473 | I43: =IFERROR(I38/I41,0) -> 61.324067 | J43: =IFERROR(J38/J41,0) -> 106.5426 | ... M43: =IFERROR(M38/M41,0) -> 0
B44: EPS Growth | D44: =IFERROR(D43/C43-1,0) -> 0.27793796 | E44: =IFERROR(E43/D43-1,0) -> 0.27006443 | F44: =IFERROR(F43/E43-1,0) -> 0.017847361 | G44: =IFERROR(G43/F43-1,0) -> -0.17782567 | H44: =IFERROR(H43/G43-1,0) -> -0.26350285 | I44: =IFERROR(I43/H43-1,0) -> 0.24433826 | J44: =IFERROR(J43/I43-1,0) -> 0.73737002 | K44: =IFERROR(K43/J43-1,0) -> 0.37155402 | ... M44: =IFERROR(M43/L43-1,0) -> -1
B46: Dividend Per shares | C46: =IFERROR('Data Sheet'!B31,0) -> 271.6 | D46: =IFERROR('Data Sheet'!C31,0) -> 272.1 | E46: =IFERROR('Data Sheet'!D31,0) -> 299.86 | F46: =IFERROR('Data Sheet'!E31,0) -> 341 | G46: =IFERROR('Data Sheet'!F31,0) -> 341.25 | H46: =IFERROR('Data Sheet'!G31,0) -> 464.61 | I46: =IFERROR('Data Sheet'!H31,0) -> 574.14 | J46: =IFERROR('Data Sheet'!I31,0) -> 1011.95 | ... M46: =IFERROR('Data Sheet'!L31,0) -> 0
B47: Dividend Peyout % of PAT | C47: =C46/C38 -> 0.20298347 | D47: =D46/D38 -> 0.15883672 | E47: =E46/E38 -> 0.13756813 | F47: =F46/F38 -> 0.15358631 | G47: =G46/G38 -> 0.18673664 | H47: =H46/H38 -> 0.34495022 | I47: =I46/I38 -> 0.34244304 | J47: =J46/J38 -> 0.34727894 | ... M47: =M46/M38 -> 0
B49: Retained Earing | C49: =IFERROR(1-C47,0) -> 0.79701653 | D49: =IFERROR(1-D47,0) -> 0.84116328 | E49: =IFERROR(1-E47,0) -> 0.86243187 | F49: =IFERROR(1-F47,0) -> 0.84641369 | G49: =IFERROR(1-G47,0) -> 0.81326336 | H49: =IFERROR(1-H47,0) -> 0.65504978 | I49: =IFERROR(1-I47,0) -> 0.65755696 | J49: =IFERROR(1-J47,0) -> 0.65272106 | ... M49: =IFERROR(1-M47,0) -> 1
A52: # | B52: Balace Sheet
B53: Equity Share Capital | C53: =IFERROR('Data Sheet'!B57,0) -> 27.16 | D53: =IFERROR('Data Sheet'!C57,0) -> 27.21 | E53: =IFERROR('Data Sheet'!D57,0) -> 27.26 | F53: =IFERROR('Data Sheet'!E57,0) -> 27.28 | G53: =IFERROR('Data Sheet'!F57,0) -> 27.3 | H53: =IFERROR('Data Sheet'!G57,0) -> 27.33 | I53: =IFERROR('Data Sheet'!H57,0) -> 27.34 | J53: =IFERROR('Data Sheet'!I57,0) -> 27.35 | ... L53: =IFERROR('Data Sheet'!K57,0) -> 27.42
B54: Reserves | C54: =IFERROR('Data Sheet'!B58,0) -> 3625.93 | D54: =IFERROR('Data Sheet'!C58,0) -> 5317.86 | E54: =IFERROR('Data Sheet'!D58,0) -> 7002.81 | F54: =IFERROR('Data Sheet'!E58,0) -> 8891.44 | G54: =IFERROR('Data Sheet'!F58,0) -> 9953.63 | H54: =IFERROR('Data Sheet'!G58,0) -> 11410.75 | I54: =IFERROR('Data Sheet'!H58,0) -> 12580.66 | J54: =IFERROR('Data Sheet'!I58,0) -> 14962.93 | ... L54: =IFERROR('Data Sheet'!K58,0) -> 21269.07
B55: Borrowings | C55: =IFERROR('Data Sheet'!B59,0) -> 22.57 | D55: =IFERROR('Data Sheet'!C59,0) -> 111.85 | E55: =IFERROR('Data Sheet'!D59,0) -> 150.84 | F55: =IFERROR('Data Sheet'!E59,0) -> 186.76 | G55: =IFERROR('Data Sheet'!F59,0) -> 249 | H55: =IFERROR('Data Sheet'!G59,0) -> 219.25 | I55: =IFERROR('Data Sheet'!H59,0) -> 107.71 | J55: =IFERROR('Data Sheet'!I59,0) -> 288.41 | ... L55: =IFERROR('Data Sheet'!K59,0) -> 458.13
B56: Other Liabilities | C56: =IFERROR('Data Sheet'!B60,0) -> 1263.35 | D56: =IFERROR('Data Sheet'!C60,0) -> 1552.16 | E56: =IFERROR('Data Sheet'!D60,0) -> 2341.32 | F56: =IFERROR('Data Sheet'!E60,0) -> 2281.35 | G56: =IFERROR('Data Sheet'!F60,0) -> 2219.79 | H56: =IFERROR('Data Sheet'!G60,0) -> 2901.28 | I56: =IFERROR('Data Sheet'!H60,0) -> 3424.12 | J56: =IFERROR('Data Sheet'!I60,0) -> 3918.95 | ... L56: =IFERROR('Data Sheet'!K60,0) -> 5419.79
B57: Total Liabilities | C57: =IFERROR('Data Sheet'!B61,0) -> 4939.01 | D57: =IFERROR('Data Sheet'!C61,0) -> 7009.08 | E57: =IFERROR('Data Sheet'!D61,0) -> 9522.23 | F57: =IFERROR('Data Sheet'!E61,0) -> 11386.83 | G57: =IFERROR('Data Sheet'!F61,0) -> 12449.72 | H57: =IFERROR('Data Sheet'!G61,0) -> 14558.61 | I57: =IFERROR('Data Sheet'!H61,0) -> 16139.83 | J57: =IFERROR('Data Sheet'!I61,0) -> 19197.64 | ... L57: =IFERROR('Data Sheet'!K61,0) -> 27174.41
B59: Fix Assets Net Block | C59: =IFERROR('Data Sheet'!B62,0) -> 789.59 | D59: =IFERROR('Data Sheet'!C62,0) -> 872.78 | E59: =IFERROR('Data Sheet'!D62,0) -> 1501.69 | F59: =IFERROR('Data Sheet'!E62,0) -> 1874.58 | G59: =IFERROR('Data Sheet'!F62,0) -> 2377.52 | H59: =IFERROR('Data Sheet'!G62,0) -> 2433.3 | I59: =IFERROR('Data Sheet'!H62,0) -> 2424.28 | J59: =IFERROR('Data Sheet'!I62,0) -> 2689.99 | ... L59: =IFERROR('Data Sheet'!K62,0) -> 3473.47
B60: Capital Work in Progress | C60: =IFERROR('Data Sheet'!B63,0) -> 94.48 | D60: =IFERROR('Data Sheet'!C63,0) -> 373.77 | E60: =IFERROR('Data Sheet'!D63,0) -> 333.21 | F60: =IFERROR('Data Sheet'!E63,0) -> 449.74 | G60: =IFERROR('Data Sheet'!F63,0) -> 312.17 | H60: =IFERROR('Data Sheet'!G63,0) -> 314.29 | I60: =IFERROR('Data Sheet'!H63,0) -> 504.78 | J60: =IFERROR('Data Sheet'!I63,0) -> 472.07 | ... L60: =IFERROR('Data Sheet'!K63,0) -> 491.47
B61: Investments | C61: =IFERROR('Data Sheet'!B64,0) -> 3388.24 | D61: =IFERROR('Data Sheet'!C64,0) -> 4987.13 | E61: =IFERROR('Data Sheet'!D64,0) -> 5580.84 | F61: =IFERROR('Data Sheet'!E64,0) -> 4922.52 | G61: =IFERROR('Data Sheet'!F64,0) -> 5748.77 | H61: =IFERROR('Data Sheet'!G64,0) -> 3902.14 | I61: =IFERROR('Data Sheet'!H64,0) -> 7720.58 | J61: =IFERROR('Data Sheet'!I64,0) -> 12320.66 | ... L61: =IFERROR('Data Sheet'!K64,0) -> 14790.9
B62: Other Assets | C62: =IFERROR('Data Sheet'!B65,0) -> 666.7 | D62: =IFERROR('Data Sheet'!C65,0) -> 775.4 | E62: =IFERROR('Data Sheet'!D65,0) -> 2106.49 | F62: =IFERROR('Data Sheet'!E65,0) -> 4139.99 | G62: =IFERROR('Data Sheet'!F65,0) -> 4011.26 | H62: =IFERROR('Data Sheet'!G65,0) -> 7908.88 | I62: =IFERROR('Data Sheet'!H65,0) -> 5490.19 | J62: =IFERROR('Data Sheet'!I65,0) -> 3714.92 | ... L62: =IFERROR('Data Sheet'!K65,0) -> 8418.57
B63: Total Non- Current Assets | C63: =IFERROR(SUM(C59:C62)-C68,0) -> 4548.81 | D63: =IFERROR(SUM(D59:D62)-D68,0) -> 6598.08 | E63: =IFERROR(SUM(E59:E62)-E68,0) -> 7847.59 | F63: =IFERROR(SUM(F59:F62)-F68,0) -> 7703.87 | G63: =IFERROR(SUM(G59:G62)-G68,0) -> 8840.02 | H63: =IFERROR(SUM(H59:H62)-H68,0) -> 7695.49 | I63: =IFERROR(SUM(I59:I62)-I68,0) -> 11982.92 | J63: =IFERROR(SUM(J59:J62)-J68,0) -> 16784.7 | ... L63: =IFERROR(SUM(L59:L62)-L68,0) -> 24798.01
B65: Receivables | C65: =IFERROR('Data Sheet'!B67,0) -> 32.64 | D65: =IFERROR('Data Sheet'!C67,0) -> 50.04 | E65: =IFERROR('Data Sheet'!D67,0) -> 68 | F65: =IFERROR('Data Sheet'!E67,0) -> 84.29 | G65: =IFERROR('Data Sheet'!F67,0) -> 86.76 | H65: =IFERROR('Data Sheet'!G67,0) -> 158.16 | I65: =IFERROR('Data Sheet'!H67,0) -> 302.04 | J65: =IFERROR('Data Sheet'!I67,0) -> 368.92 | ... L65: =IFERROR('Data Sheet'!K67,0) -> 549.64
B66: Inventory | C66: =IFERROR('Data Sheet'!B68,0) -> 308.39 | D66: =IFERROR('Data Sheet'!C68,0) -> 335.9 | E66: =IFERROR('Data Sheet'!D68,0) -> 394.64 | F66: =IFERROR('Data Sheet'!E68,0) -> 633.38 | G66: =IFERROR('Data Sheet'!F68,0) -> 572.35 | H66: =IFERROR('Data Sheet'!G68,0) -> 874.6 | I66: =IFERROR('Data Sheet'!H68,0) -> 1132.4 | J66: =IFERROR('Data Sheet'!I68,0) -> 1278.44 | ... L66: =IFERROR('Data Sheet'!K68,0) -> 1563.75
B67: Cash & Bank | C67: =IFERROR('Data Sheet'!B69,0) -> 49.17 | D67: =IFERROR('Data Sheet'!C69,0) -> 25.06 | E67: =IFERROR('Data Sheet'!D69,0) -> 1212 | F67: =IFERROR('Data Sheet'!E69,0) -> 2965.29 | G67: =IFERROR('Data Sheet'!F69,0) -> 2950.59 | H67: =IFERROR('Data Sheet'!G69,0) -> 5830.36 | I67: =IFERROR('Data Sheet'!H69,0) -> 2722.47 | J67: =IFERROR('Data Sheet'!I69,0) -> 765.58 | ... L67: =IFERROR('Data Sheet'!K69,0) -> 263.01
B68: Total Current Assets | C68: =IFERROR(SUM(C65:C67),0) -> 390.2 | D68: =IFERROR(SUM(D65:D67),0) -> 411 | E68: =IFERROR(SUM(E65:E67),0) -> 1674.64 | F68: =IFERROR(SUM(F65:F67),0) -> 3682.96 | G68: =IFERROR(SUM(G65:G67),0) -> 3609.7 | H68: =IFERROR(SUM(H65:H67),0) -> 6863.12 | I68: =IFERROR(SUM(I65:I67),0) -> 4156.91 | J68: =IFERROR(SUM(J65:J67),0) -> 2412.94 | ... L68: =IFERROR(SUM(L65:L67),0) -> 2376.4
B69: Total Assets | C69: =IFERROR(SUM(C63,C68),0) -> 4939.01 | D69: =IFERROR(SUM(D63,D68),0) -> 7009.08 | E69: =IFERROR(SUM(E63,E68),0) -> 9522.23 | F69: =IFERROR(SUM(F63,F68),0) -> 11386.83 | G69: =IFERROR(SUM(G63,G68),0) -> 12449.72 | H69: =IFERROR(SUM(H63,H68),0) -> 14558.61 | I69: =IFERROR(SUM(I63,I68),0) -> 16139.83 | J69: =IFERROR(SUM(J63,J68),0) -> 19197.64 | ... L69: =IFERROR(SUM(L63,L68),0) -> 27174.41
B71: Check | C71: =C69=C57 -> TRUE | D71: =D69=D57 -> TRUE | E71: =E69=E57 -> TRUE | F71: =F69=F57 -> TRUE | G71: =G69=G57 -> TRUE | H71: =H69=H57 -> TRUE | I71: =I69=I57 -> TRUE | J71: =J69=J57 -> TRUE | ... L71: =L69=L57 -> TRUE
A74: # | B74: Cash Flow Statement
B76: Operating Activity
B77: Profit from operations | C77: =IFERROR('Cashflow raw data'!E4,0) -> 1719 | D77: =IFERROR('Cashflow raw data'!F4,0) -> 2196 | E77: =IFERROR('Cashflow raw data'!G4,0) -> 2851 | F77: =IFERROR('Cashflow raw data'!H4,0) -> 2941 | G77: =IFERROR('Cashflow raw data'!I4,0) -> 2236 | H77: =IFERROR('Cashflow raw data'!J4,0) -> 1912 | I77: =IFERROR('Cashflow raw data'!K4,0) -> 2172 | J77: =IFERROR('Cashflow raw data'!L4,0) -> 3527 | ... L77: =IFERROR('Cashflow raw data'!N4,0) -> 4849
B78: Receivables | C78: =IFERROR('Cashflow raw data'!E5,0) -> -22 | D78: =IFERROR('Cashflow raw data'!F5,0) -> -17 | E78: =IFERROR('Cashflow raw data'!G5,0) -> -18 | F78: =IFERROR('Cashflow raw data'!H5,0) -> -18 | G78: =IFERROR('Cashflow raw data'!I5,0) -> 0 | H78: =IFERROR('Cashflow raw data'!J5,0) -> -73 | I78: =IFERROR('Cashflow raw data'!K5,0) -> -147 | J78: =IFERROR('Cashflow raw data'!L5,0) -> -59 | ... L78: =IFERROR('Cashflow raw data'!N5,0) -> -176
B79: Inventory | C79: =IFERROR('Cashflow raw data'!E6,0) -> -104 | D79: =IFERROR('Cashflow raw data'!F6,0) -> -28 | E79: =IFERROR('Cashflow raw data'!G6,0) -> -59 | F79: =IFERROR('Cashflow raw data'!H6,0) -> -239 | G79: =IFERROR('Cashflow raw data'!I6,0) -> 61 | H79: =IFERROR('Cashflow raw data'!J6,0) -> -302 | I79: =IFERROR('Cashflow raw data'!K6,0) -> -258 | J79: =IFERROR('Cashflow raw data'!L6,0) -> -146 | ... L79: =IFERROR('Cashflow raw data'!N6,0) -> -154
B80: Payables | C80: =IFERROR('Cashflow raw data'!E7,0) -> 241 | D80: =IFERROR('Cashflow raw data'!F7,0) -> 110 | E80: =IFERROR('Cashflow raw data'!G7,0) -> 407 | F80: =IFERROR('Cashflow raw data'!H7,0) -> 62 | G80: =IFERROR('Cashflow raw data'!I7,0) -> -235 | H80: =IFERROR('Cashflow raw data'!J7,0) -> 495 | I80: =IFERROR('Cashflow raw data'!K7,0) -> 283 | J80: =IFERROR('Cashflow raw data'!L7,0) -> 22 | ... L80: =IFERROR('Cashflow raw data'!N7,0) -> 440
B81: Loans Advances | C81: =IFERROR('Cashflow raw data'!E8,0) -> -12 | D81: =IFERROR('Cashflow raw data'!F8,0) -> 6 | E81: =IFERROR('Cashflow raw data'!G8,0) -> 0 | F81: =IFERROR('Cashflow raw data'!H8,0) -> -1 | G81: =IFERROR('Cashflow raw data'!I8,0) -> 1 | H81: =IFERROR('Cashflow raw data'!J8,0) -> 0 | I81: =IFERROR('Cashflow raw data'!K8,0) -> 0 | J81: =IFERROR('Cashflow raw data'!L8,0) -> 0 | ... L81: =IFERROR('Cashflow raw data'!N8,0) -> 0
B82: Other WC items | C82: =IFERROR('Cashflow raw data'!E9,0) -> 160 | D82: =IFERROR('Cashflow raw data'!F9,0) -> 92 | E82: =IFERROR('Cashflow raw data'!G9,0) -> 109 | F82: =IFERROR('Cashflow raw data'!H9,0) -> -262 | G82: =IFERROR('Cashflow raw data'!I9,0) -> 259 | H82: =IFERROR('Cashflow raw data'!J9,0) -> 115 | I82: =IFERROR('Cashflow raw data'!K9,0) -> -10 | J82: =IFERROR('Cashflow raw data'!L9,0) -> 249 | ... L82: =IFERROR('Cashflow raw data'!N9,0) -> 101
B83: Working capital changes | C83: =IFERROR('Cashflow raw data'!E10,0) -> 263 | D83: =IFERROR('Cashflow raw data'!F10,0) -> 163 | E83: =IFERROR('Cashflow raw data'!G10,0) -> 438 | F83: =IFERROR('Cashflow raw data'!H10,0) -> -457 | G83: =IFERROR('Cashflow raw data'!I10,0) -> 86 | H83: =IFERROR('Cashflow raw data'!J10,0) -> 235 | I83: =IFERROR('Cashflow raw data'!K10,0) -> -131 | J83: =IFERROR('Cashflow raw data'!L10,0) -> 66 | ... L83: =IFERROR('Cashflow raw data'!N10,0) -> 211
B84: Direct taxes | C84: =IFERROR('Cashflow raw data'!E11,0) -> -519 | D84: =IFERROR('Cashflow raw data'!F11,0) -> -652 | E84: =IFERROR('Cashflow raw data'!G11,0) -> -807 | F84: =IFERROR('Cashflow raw data'!H11,0) -> -908 | G84: =IFERROR('Cashflow raw data'!I11,0) -> -628 | H84: =IFERROR('Cashflow raw data'!J11,0) -> -457 | I84: =IFERROR('Cashflow raw data'!K11,0) -> -514 | J84: =IFERROR('Cashflow raw data'!L11,0) -> -770 | ... L84: =IFERROR('Cashflow raw data'!N11,0) -> -1080
B85: Cash from Operating Activity (A) | C85: =SUM(C77:C84) -> 1726 | D85: =SUM(D77:D84) -> 1870 | E85: =SUM(E77:E84) -> 2921 | F85: =SUM(F77:F84) -> 1118 | G85: =SUM(G77:G84) -> 1780 | H85: =SUM(H77:H84) -> 1925 | I85: =SUM(I77:I84) -> 1395 | J85: =SUM(J77:J84) -> 2889 | ... L85: =SUM(L77:L84) -> 4191
B87: Investing Activity
B88: Fixed assets purchased | C88: =IFERROR('Cashflow raw data'!E13,0) -> -510 | D88: =IFERROR('Cashflow raw data'!F13,0) -> -548 | E88: =IFERROR('Cashflow raw data'!G13,0) -> -748 | F88: =IFERROR('Cashflow raw data'!H13,0) -> -792 | G88: =IFERROR('Cashflow raw data'!I13,0) -> -546 | H88: =IFERROR('Cashflow raw data'!J13,0) -> -532 | I88: =IFERROR('Cashflow raw data'!K13,0) -> -641 | J88: =IFERROR('Cashflow raw data'!L13,0) -> -682 | ... L88: =IFERROR('Cashflow raw data'!N13,0) -> -1039
B89: Fixed assets sold | C89: =IFERROR('Cashflow raw data'!E14,0) -> 1 | D89: =IFERROR('Cashflow raw data'!F14,0) -> 1 | E89: =IFERROR('Cashflow raw data'!G14,0) -> 3 | F89: =IFERROR('Cashflow raw data'!H14,0) -> 2 | G89: =IFERROR('Cashflow raw data'!I14,0) -> 1 | H89: =IFERROR('Cashflow raw data'!J14,0) -> 17 | I89: =IFERROR('Cashflow raw data'!K14,0) -> 2 | J89: =IFERROR('Cashflow raw data'!L14,0) -> 9 | ... L89: =IFERROR('Cashflow raw data'!N14,0) -> 11
B90: Investments purchased | C90: =IFERROR('Cashflow raw data'!E15,0) -> -662 | D90: =IFERROR('Cashflow raw data'!F15,0) -> -4247 | E90: =IFERROR('Cashflow raw data'!G15,0) -> -6464 | F90: =IFERROR('Cashflow raw data'!H15,0) -> -7929 | G90: =IFERROR('Cashflow raw data'!I15,0) -> -8746 | H90: =IFERROR('Cashflow raw data'!J15,0) -> -3983 | I90: =IFERROR('Cashflow raw data'!K15,0) -> -7134 | J90: =IFERROR('Cashflow raw data'!L15,0) -> -9103 | ... L90: =IFERROR('Cashflow raw data'!N15,0) -> -6939
B91: Investments sold | C91: =IFERROR('Cashflow raw data'!E16,0) -> 158 | D91: =IFERROR('Cashflow raw data'!F16,0) -> 3051 | E91: =IFERROR('Cashflow raw data'!G16,0) -> 6124 | F91: =IFERROR('Cashflow raw data'!H16,0) -> 9051 | G91: =IFERROR('Cashflow raw data'!I16,0) -> 8176 | H91: =IFERROR('Cashflow raw data'!J16,0) -> 5971 | I91: =IFERROR('Cashflow raw data'!K16,0) -> 3500 | J91: =IFERROR('Cashflow raw data'!L16,0) -> 5080 | ... L91: =IFERROR('Cashflow raw data'!N16,0) -> 6826
B92: Interest received | C92: =IFERROR('Cashflow raw data'!E17,0) -> 4 | D92: =IFERROR('Cashflow raw data'!F17,0) -> 3 | E92: =IFERROR('Cashflow raw data'!G17,0) -> 12 | F92: =IFERROR('Cashflow raw data'!H17,0) -> 90 | G92: =IFERROR('Cashflow raw data'!I17,0) -> 204 | H92: =IFERROR('Cashflow raw data'!J17,0) -> 192 | I92: =IFERROR('Cashflow raw data'!K17,0) -> 398 | J92: =IFERROR('Cashflow raw data'!L17,0) -> 204 | ... L92: =IFERROR('Cashflow raw data'!N17,0) -> 188
B93: Dividends received | C93: =IFERROR('Cashflow raw data'!E18,0) -> 107 | D93: =IFERROR('Cashflow raw data'!F18,0) -> 0 | E93: =IFERROR('Cashflow raw data'!G18,0) -> 52 | F93: =IFERROR('Cashflow raw data'!H18,0) -> 65 | G93: =IFERROR('Cashflow raw data'!I18,0) -> 68 | H93: =IFERROR('Cashflow raw data'!J18,0) -> 0 | I93: =IFERROR('Cashflow raw data'!K18,0) -> 27 | J93: =IFERROR('Cashflow raw data'!L18,0) -> 41 | ... L93: =IFERROR('Cashflow raw data'!N18,0) -> 136
B94: Investment in group cos | C94: =IFERROR('Cashflow raw data'!E19,0) -> -109 | D94: =IFERROR('Cashflow raw data'!F19,0) -> -39 | E94: =IFERROR('Cashflow raw data'!G19,0) -> -16 | F94: =IFERROR('Cashflow raw data'!H19,0) -> -30 | G94: =IFERROR('Cashflow raw data'!I19,0) -> -1 | H94: =IFERROR('Cashflow raw data'!J19,0) -> 0 | I94: =IFERROR('Cashflow raw data'!K19,0) -> 0 | J94: =IFERROR('Cashflow raw data'!L19,0) -> 0 | ... L94: =IFERROR('Cashflow raw data'!N19,0) -> 0
B95: Other investing items | C95: =IFERROR('Cashflow raw data'!E20,0) -> 9 | D95: =IFERROR('Cashflow raw data'!F20,0) -> 36 | E95: =IFERROR('Cashflow raw data'!G20,0) -> -1106 | F95: =IFERROR('Cashflow raw data'!H20,0) -> -1117 | G95: =IFERROR('Cashflow raw data'!I20,0) -> -665 | H95: =IFERROR('Cashflow raw data'!J20,0) -> -3290 | I95: =IFERROR('Cashflow raw data'!K20,0) -> 2864 | J95: =IFERROR('Cashflow raw data'!L20,0) -> 2055 | ... L95: =IFERROR('Cashflow raw data'!N20,0) -> -1643
B96: Cash from Investing Activity (B) | C96: =SUM(C88:C95) -> -1002 | D96: =SUM(D88:D95) -> -1743 | E96: =SUM(E88:E95) -> -2143 | F96: =SUM(F88:F95) -> -660 | G96: =SUM(G88:G95) -> -1509 | H96: =SUM(H88:H95) -> -1625 | I96: =SUM(I88:I95) -> -984 | J96: =SUM(J88:J95) -> -2396 | ... L96: =SUM(L88:L95) -> -2460
B98: Cash from Financing Activity
B99: Proceeds from shares | C99: =IFERROR('Cashflow raw data'!E22,0) -> 5 | D99: =IFERROR('Cashflow raw data'!F22,0) -> 6 | E99: =IFERROR('Cashflow raw data'!G22,0) -> 19 | F99: =IFERROR('Cashflow raw data'!H22,0) -> 36 | G99: =IFERROR('Cashflow raw data'!I22,0) -> 29 | H99: =IFERROR('Cashflow raw data'!J22,0) -> 38 | I99: =IFERROR('Cashflow raw data'!K22,0) -> 6 | J99: =IFERROR('Cashflow raw data'!L22,0) -> 11 | ... L99: =IFERROR('Cashflow raw data'!N22,0) -> 97
B100: Proceeds from borrowings | C100: =IFERROR('Cashflow raw data'!E23,0) -> 0 | D100: =IFERROR('Cashflow raw data'!F23,0) -> 389 | E100: =IFERROR('Cashflow raw data'!G23,0) -> 495 | F100: =IFERROR('Cashflow raw data'!H23,0) -> 369 | G100: =IFERROR('Cashflow raw data'!I23,0) -> 267 | H100: =IFERROR('Cashflow raw data'!J23,0) -> 40 | I100: =IFERROR('Cashflow raw data'!K23,0) -> 32 | J100: =IFERROR('Cashflow raw data'!L23,0) -> 202 | ... L100: =IFERROR('Cashflow raw data'!N23,0) -> 38
B101: Repayment of borrowings | C101: =IFERROR('Cashflow raw data'!E24,0) -> 0 | D101: =IFERROR('Cashflow raw data'!F24,0) -> -345 | E101: =IFERROR('Cashflow raw data'!G24,0) -> -456 | F101: =IFERROR('Cashflow raw data'!H24,0) -> -344 | G101: =IFERROR('Cashflow raw data'!I24,0) -> -298 | H101: =IFERROR('Cashflow raw data'!J24,0) -> -27 | I101: =IFERROR('Cashflow raw data'!K24,0) -> -137 | J101: =IFERROR('Cashflow raw data'!L24,0) -> -20 | ... L101: =IFERROR('Cashflow raw data'!N24,0) -> -43
B102: Interest paid fin | C102: =IFERROR('Cashflow raw data'!E25,0) -> -2 | D102: =IFERROR('Cashflow raw data'!F25,0) -> -2 | E102: =IFERROR('Cashflow raw data'!G25,0) -> -3 | F102: =IFERROR('Cashflow raw data'!H25,0) -> -5 | G102: =IFERROR('Cashflow raw data'!I25,0) -> -8 | H102: =IFERROR('Cashflow raw data'!J25,0) -> -16 | I102: =IFERROR('Cashflow raw data'!K25,0) -> -19 | J102: =IFERROR('Cashflow raw data'!L25,0) -> -18 | ... L102: =IFERROR('Cashflow raw data'!N25,0) -> -37
B103: Dividends paid | C103: =IFERROR('Cashflow raw data'!E26,0) -> -407 | D103: =IFERROR('Cashflow raw data'!F26,0) -> 0 | E103: =IFERROR('Cashflow raw data'!G26,0) -> -272 | F103: =IFERROR('Cashflow raw data'!H26,0) -> -300 | G103: =IFERROR('Cashflow raw data'!I26,0) -> -682 | H103: =IFERROR('Cashflow raw data'!J26,0) -> 0 | I103: =IFERROR('Cashflow raw data'!K26,0) -> -465 | J103: =IFERROR('Cashflow raw data'!L26,0) -> -574 | ... L103: =IFERROR('Cashflow raw data'!N26,0) -> -1397
B104: Financial liabilities | C104: =IFERROR('Cashflow raw data'!E27,0) -> 0 | D104: =IFERROR('Cashflow raw data'!F27,0) -> 0 | E104: =IFERROR('Cashflow raw data'!G27,0) -> 0 | F104: =IFERROR('Cashflow raw data'!H27,0) -> 0 | G104: =IFERROR('Cashflow raw data'!I27,0) -> -40 | H104: =IFERROR('Cashflow raw data'!J27,0) -> -39 | I104: =IFERROR('Cashflow raw data'!K27,0) -> -17 | J104: =IFERROR('Cashflow raw data'!L27,0) -> -19 | ... L104: =IFERROR('Cashflow raw data'!N27,0) -> -56
B105: Other financing items | C105: =IFERROR('Cashflow raw data'!E28,0) -> -61 | D105: =IFERROR('Cashflow raw data'!F28,0) -> -23 | E105: =IFERROR('Cashflow raw data'!G28,0) -> -45 | F105: =IFERROR('Cashflow raw data'!H28,0) -> -48 | G105: =IFERROR('Cashflow raw data'!I28,0) -> -126 | H105: =IFERROR('Cashflow raw data'!J28,0) -> -11 | I105: =IFERROR('Cashflow raw data'!K28,0) -> 5 | J105: =IFERROR('Cashflow raw data'!L28,0) -> 0 | ... L105: =IFERROR('Cashflow raw data'!N28,0) -> 0
B106: Cash from Financing Activity © | C106: =SUM(C99:C105) -> -465 | D106: =SUM(D99:D105) -> 25 | E106: =SUM(E99:E105) -> -262 | F106: =SUM(F99:F105) -> -292 | G106: =SUM(G99:G105) -> -858 | H106: =SUM(H99:H105) -> -15 | I106: =SUM(I99:I105) -> -595 | J106: =SUM(J99:J105) -> -418 | ... L106: =SUM(L99:L105) -> -1398
B108: Net Cash Flow (A+B+C) | C108: =IFERROR(SUM(C85,C96,C106),0) -> 259 | D108: =IFERROR(SUM(D85,D96,D106),0) -> 152 | E108: =IFERROR(SUM(E85,E96,E106),0) -> 516 | F108: =IFERROR(SUM(F85,F96,F106),0) -> 166 | G108: =IFERROR(SUM(G85,G96,G106),0) -> -587 | H108: =IFERROR(SUM(H85,H96,H106),0) -> 285 | I108: =IFERROR(SUM(I85,I96,I106),0) -> -184 | J108: =IFERROR(SUM(J85,J96,J106),0) -> 75 | ... L108: =IFERROR(SUM(L85,L96,L106),0) -> 333

Sheet Common size statement
B1: Common Size Statement
B4: Perticular | C4: =HistoricalIFS!C3 -> 42460 | D4: =HistoricalIFS!D3 -> 42825 | E4: =HistoricalIFS!E3 -> 43190 | F4: =HistoricalIFS!F3 -> 43555 | G4: =HistoricalIFS!G3 -> 43921 | H4: =HistoricalIFS!H3 -> 44286 | I4: =HistoricalIFS!I3 -> 44651 | J4: =HistoricalIFS!J3 -> 45016 | ... L4: =HistoricalIFS!L3 -> 45747
B5: Sales | C5: =IFERROR(HistoricalIFS!C6/HistoricalIFS!C6,0) -> 1 | D5: =IFERROR(HistoricalIFS!D6/HistoricalIFS!D6,0) -> 1 | E5: =IFERROR(HistoricalIFS!E6/HistoricalIFS!E6,0) -> 1 | F5: =IFERROR(HistoricalIFS!F6/HistoricalIFS!F6,0) -> 1 | G5: =IFERROR(HistoricalIFS!G6/HistoricalIFS!G6,0) -> 1 | H5: =IFERROR(HistoricalIFS!H6/HistoricalIFS!H6,0) -> 1 | I5: =IFERROR(HistoricalIFS!I6/HistoricalIFS!I6,0) -> 1 | J5: =IFERROR(HistoricalIFS!J6/HistoricalIFS!J6,0) -> 1 | ... L5: =IFERROR(HistoricalIFS!L6/HistoricalIFS!L6,0) -> 1
B6: COGS | C6: =IFERROR(HistoricalIFS!C9/HistoricalIFS!C6,0) -> 0.64887923 | D6: =IFERROR(HistoricalIFS!D9/HistoricalIFS!D6,0) -> 0.61869434 | E6: =IFERROR(HistoricalIFS!E9/HistoricalIFS!E6,0) -> 0.61149743 | F6: =IFERROR(HistoricalIFS!F9/HistoricalIFS!F6,0) -> 0.62185697 | G6: =IFERROR(HistoricalIFS!G9/HistoricalIFS!G6,0) -> 0.66792337 | H6: =IFERROR(HistoricalIFS!H9/HistoricalIFS!H6,0) -> 0.71797692 | I6: =IFERROR(HistoricalIFS!I9/HistoricalIFS!I6,0) -> 0.69605927 | J6: =IFERROR(HistoricalIFS!J9/HistoricalIFS!J6,0) -> 0.67094441 | ... L6: =IFERROR(HistoricalIFS!L9/HistoricalIFS!L6,0) -> 0.64869544
B7: Gross Profit | C7: =IFERROR(HistoricalIFS!C12/HistoricalIFS!C6,0) -> 0.35112077 | D7: =IFERROR(HistoricalIFS!D12/HistoricalIFS!D6,0) -> 0.38130566 | E7: =IFERROR(HistoricalIFS!E12/HistoricalIFS!E6,0) -> 0.38850257 | F7: =IFERROR(HistoricalIFS!F12/HistoricalIFS!F6,0) -> 0.37814303 | G7: =IFERROR(HistoricalIFS!G12/HistoricalIFS!G6,0) -> 0.33207663 | H7: =IFERROR(HistoricalIFS!H12/HistoricalIFS!H6,0) -> 0.28202308 | I7: =IFERROR(HistoricalIFS!I12/HistoricalIFS!I6,0) -> 0.30394073 | J7: =IFERROR(HistoricalIFS!J12/HistoricalIFS!J6,0) -> 0.32905559 | ... L7: =IFERROR(HistoricalIFS!L12/HistoricalIFS!L6,0) -> 0.35130456
B8: Selling & General Expenses | C8: =IFERROR(HistoricalIFS!C15/HistoricalIFS!C6,0) -> 0.077412019 | D8: =IFERROR(HistoricalIFS!D15/HistoricalIFS!D6,0) -> 0.072163234 | E8: =IFERROR(HistoricalIFS!E15/HistoricalIFS!E6,0) -> 0.075212829 | F8: =IFERROR(HistoricalIFS!F15/HistoricalIFS!F6,0) -> 0.081703082 | G8: =IFERROR(HistoricalIFS!G15/HistoricalIFS!G6,0) -> 0.093602722 | H8: =IFERROR(HistoricalIFS!H15/HistoricalIFS!H6,0) -> 0.077532438 | I8: =IFERROR(HistoricalIFS!I15/HistoricalIFS!I6,0) -> 0.09248162 | J8: =IFERROR(HistoricalIFS!J15/HistoricalIFS!J6,0) -> 0.090468336 | ... L8: =IFERROR(HistoricalIFS!L15/HistoricalIFS!L6,0) -> 0.10104052
B9: EBIDTA | C9: =IFERROR(HistoricalIFS!C17/HistoricalIFS!C6,0) -> 0.27370875 | D9: =IFERROR(HistoricalIFS!D17/HistoricalIFS!D6,0) -> 0.30914243 | E9: =IFERROR(HistoricalIFS!E17/HistoricalIFS!E6,0) -> 0.31328974 | F9: =IFERROR(HistoricalIFS!F17/HistoricalIFS!F6,0) -> 0.29643995 | G9: =IFERROR(HistoricalIFS!G17/HistoricalIFS!G6,0) -> 0.23847391 | H9: =IFERROR(HistoricalIFS!H17/HistoricalIFS!H6,0) -> 0.20449065 | I9: =IFERROR(HistoricalIFS!I17/HistoricalIFS!I6,0) -> 0.21145911 | J9: =IFERROR(HistoricalIFS!J17/HistoricalIFS!J6,0) -> 0.23858725 | ... L9: =IFERROR(HistoricalIFS!L17/HistoricalIFS!L6,0) -> 0.25026404
B10: Intreste | C10: =IFERROR(HistoricalIFS!C20/HistoricalIFS!C6,0) -> 0.00034340548 | D10: =IFERROR(HistoricalIFS!D20/HistoricalIFS!D6,0) -> 0.00050615922 | E10: =IFERROR(HistoricalIFS!E20/HistoricalIFS!E6,0) -> 0.00059565241 | F10: =IFERROR(HistoricalIFS!F20/HistoricalIFS!F6,0) -> 0.00074818364 | G10: =IFERROR(HistoricalIFS!G20/HistoricalIFS!G6,0) -> 0.002062581 | H10: =IFERROR(HistoricalIFS!H20/HistoricalIFS!H6,0) -> 0.0018863922 | I10: =IFERROR(HistoricalIFS!I20/HistoricalIFS!I6,0) -> 0.0018236852 | J10: =IFERROR(HistoricalIFS!J20/HistoricalIFS!J6,0) -> 0.0019401503 | ... L10: =IFERROR(HistoricalIFS!L20/HistoricalIFS!L6,0) -> 0.0028796498
B11: Depreciation | C11: =IFERROR(HistoricalIFS!C23/HistoricalIFS!C6,0) -> 0.022126976 | D11: =IFERROR(HistoricalIFS!D23/HistoricalIFS!D6,0) -> 0.021868637 | E11: =IFERROR(HistoricalIFS!E23/HistoricalIFS!E6,0) -> 0.024908087 | F11: =IFERROR(HistoricalIFS!F23/HistoricalIFS!F6,0) -> 0.030650011 | G11: =IFERROR(HistoricalIFS!G23/HistoricalIFS!G6,0) -> 0.041682052 | H11: =IFERROR(HistoricalIFS!H23/HistoricalIFS!H6,0) -> 0.051687146 | I11: =IFERROR(HistoricalIFS!I23/HistoricalIFS!I6,0) -> 0.043885945 | J11: =IFERROR(HistoricalIFS!J23/HistoricalIFS!J6,0) -> 0.036435635 | ... L11: =IFERROR(HistoricalIFS!L23/HistoricalIFS!L6,0) -> 0.038649522
B12: Earning Before Intreste and Tax | C12: =IFERROR(HistoricalIFS!C26/HistoricalIFS!C6,0) -> 0.25158177 | D12: =IFERROR(HistoricalIFS!D26/HistoricalIFS!D6,0) -> 0.28727379 | E12: =IFERROR(HistoricalIFS!E26/HistoricalIFS!E6,0) -> 0.28838165 | F12: =IFERROR(HistoricalIFS!F26/HistoricalIFS!F6,0) -> 0.26578994 | G12: =IFERROR(HistoricalIFS!G26/HistoricalIFS!G6,0) -> 0.19679186 | H12: =IFERROR(HistoricalIFS!H26/HistoricalIFS!H6,0) -> 0.1528035 | I12: =IFERROR(HistoricalIFS!I26/HistoricalIFS!I6,0) -> 0.16757317 | J12: =IFERROR(HistoricalIFS!J26/HistoricalIFS!J6,0) -> 0.20215161 | ... L12: =IFERROR(HistoricalIFS!L26/HistoricalIFS!L6,0) -> 0.21161452
B13: Earing Before Tax | C13: =IFERROR(HistoricalIFS!C29/HistoricalIFS!C6,0) -> 0.25123837 | D13: =IFERROR(HistoricalIFS!D29/HistoricalIFS!D6,0) -> 0.28676763 | E13: =IFERROR(HistoricalIFS!E29/HistoricalIFS!E6,0) -> 0.287786 | F13: =IFERROR(HistoricalIFS!F29/HistoricalIFS!F6,0) -> 0.26504176 | G13: =IFERROR(HistoricalIFS!G29/HistoricalIFS!G6,0) -> 0.19472928 | H13: =IFERROR(HistoricalIFS!H29/HistoricalIFS!H6,0) -> 0.15091711 | I13: =IFERROR(HistoricalIFS!I29/HistoricalIFS!I6,0) -> 0.16574948 | J13: =IFERROR(HistoricalIFS!J29/HistoricalIFS!J6,0) -> 0.20021146 | ... L13: =IFERROR(HistoricalIFS!L29/HistoricalIFS!L6,0) -> 0.20873487
B14: Other Income | C14: =IFERROR(HistoricalIFS!C32/HistoricalIFS!C6,0) -> 0.052792113 | D14: =IFERROR(HistoricalIFS!D32/HistoricalIFS!D6,0) -> 0.059209254 | E14: =IFERROR(HistoricalIFS!E32/HistoricalIFS!E6,0) -> 0.059750406 | F14: =IFERROR(HistoricalIFS!F32/HistoricalIFS!F6,0) -> 0.071517374 | G14: =IFERROR(HistoricalIFS!G32/HistoricalIFS!G6,0) -> 0.062535096 | H14: =IFERROR(HistoricalIFS!H32/HistoricalIFS!H6,0) -> 0.055312 | I14: =IFERROR(HistoricalIFS!I32/HistoricalIFS!I6,0) -> 0.0481315 | J14: =IFERROR(HistoricalIFS!J32/HistoricalIFS!J6,0) -> 0.062881089 | ... L14: =IFERROR(HistoricalIFS!L32/HistoricalIFS!L6,0) -> 0.10567743
B15: Tax | C15: =IFERROR(HistoricalIFS!C35/HistoricalIFS!C6,0) -> 0.087289786 | D15: =IFERROR(HistoricalIFS!D35/HistoricalIFS!D6,0) -> 0.10241193 | E15: =IFERROR(HistoricalIFS!E35/HistoricalIFS!E6,0) -> 0.10439868 | F15: =IFERROR(HistoricalIFS!F35/HistoricalIFS!F6,0) -> 0.10993502 | G15: =IFERROR(HistoricalIFS!G35/HistoricalIFS!G6,0) -> 0.057622264 | H15: =IFERROR(HistoricalIFS!H35/HistoricalIFS!H6,0) -> 0.051775445 | I15: =IFERROR(HistoricalIFS!I35/HistoricalIFS!I6,0) -> 0.051069983 | J15: =IFERROR(HistoricalIFS!J35/HistoricalIFS!J6,0) -> 0.061326614 | ... L15: =IFERROR(HistoricalIFS!L35/HistoricalIFS!L6,0) -> 0.063519225
B16: Net Profit (PAT) | C16: =IFERROR(HistoricalIFS!C38/HistoricalIFS!C6,0) -> 0.21674069 | D16: =IFERROR(HistoricalIFS!D38/HistoricalIFS!D6,0) -> 0.24356495 | E16: =IFERROR(HistoricalIFS!E38/HistoricalIFS!E6,0) -> 0.24313773 | F16: =IFERROR(HistoricalIFS!F38/HistoricalIFS!F6,0) -> 0.22662411 | G16: =IFERROR(HistoricalIFS!G38/HistoricalIFS!G6,0) -> 0.19964211 | H16: =IFERROR(HistoricalIFS!H38/HistoricalIFS!H6,0) -> 0.15445366 | I16: =IFERROR(HistoricalIFS!I38/HistoricalIFS!I6,0) -> 0.162811 | J16: =IFERROR(HistoricalIFS!J38/HistoricalIFS!J6,0) -> 0.20176594 | ... L16: =IFERROR(HistoricalIFS!L38/HistoricalIFS!L6,0) -> 0.25089307
